<?xml version="1.0" encoding="windows-1252" ?>
<!DOCTYPE Entity SYSTEM "jbo_03_01.dtd">
<!---->
<Entity
  xmlns="http://xmlns.oracle.com/bc4j"
  Name="MmMtlRcptEO"
  Version="12.1.3.10.8"
  DBObjectType="table"
  DBObjectName="MM$MTL$RCPT"
  AliasName="MmMtlRcptEO"
  BindingStyle="OracleName"
  RowClass="mmreceiptmtl.model.entities.MmMtlRcptEOImpl"
  xmlns:validation="http://xmlns.oracle.com/adfm/validation">
  <DesignTime>
    <Attr Name="_codeGenFlag2" Value="Init|Access|DML"/>
    <Attr Name="_isCodegen" Value="true"/>
  </DesignTime>
  <Attribute
    Name="CldId"
    IsUnique="true"
    IsNotNull="true"
    Precision="4"
    ColumnName="CLD_ID"
    SQLType="VARCHAR"
    Type="java.lang.String"
    ColumnType="VARCHAR2"
    TableName="MM$MTL$RCPT"
    PrimaryKey="true"
    RetrievedOnInsert="true">
    <DesignTime>
      <Attr Name="_DisplaySize" Value="4"/>
    </DesignTime>
  </Attribute>
  <Attribute
    Name="SlocId"
    IsUnique="true"
    IsNotNull="true"
    Precision="5"
    Scale="0"
    ColumnName="SLOC_ID"
    SQLType="NUMERIC"
    Type="java.lang.Integer"
    ColumnType="NUMBER"
    TableName="MM$MTL$RCPT"
    PrimaryKey="true"
    RetrievedOnInsert="true"/>
  <Attribute
    Name="OrgId"
    IsUnique="true"
    IsNotNull="true"
    Precision="2"
    ColumnName="ORG_ID"
    SQLType="VARCHAR"
    Type="java.lang.String"
    ColumnType="VARCHAR2"
    TableName="MM$MTL$RCPT"
    PrimaryKey="true"
    RetrievedOnInsert="true">
    <DesignTime>
      <Attr Name="_DisplaySize" Value="2"/>
    </DesignTime>
  </Attribute>
  <Attribute
    Name="WhId"
    IsUnique="true"
    IsNotNull="true"
    Precision="20"
    ColumnName="WH_ID"
    SQLType="VARCHAR"
    Type="java.lang.String"
    ColumnType="VARCHAR2"
    TableName="MM$MTL$RCPT"
    PrimaryKey="true"
    RetrievedOnInsert="true">
    <DesignTime>
      <Attr Name="_DisplaySize" Value="20"/>
    </DesignTime>
  </Attribute>
  <Attribute
    Name="DocId"
    IsNotNull="true"
    Precision="40"
    ColumnName="DOC_ID"
    SQLType="VARCHAR"
    Type="java.lang.String"
    ColumnType="VARCHAR2"
    TableName="MM$MTL$RCPT"
    PrimaryKey="true"
    RetrievedOnInsert="true">
    <DesignTime>
      <Attr Name="_DisplaySize" Value="40"/>
    </DesignTime>
  </Attribute>
  <Attribute
    Name="DocDt"
    ColumnName="DOC_DT"
    SQLType="TIMESTAMP"
    Type="oracle.jbo.domain.Timestamp"
    ColumnType="TIMESTAMP"
    TableName="MM$MTL$RCPT"
    RetrievedOnInsert="true"/>
  <Attribute
    Name="FyId"
    IsUnique="true"
    Precision="5"
    Scale="0"
    ColumnName="FY_ID"
    SQLType="NUMERIC"
    Type="java.lang.Integer"
    ColumnType="NUMBER"
    TableName="MM$MTL$RCPT"
    RetrievedOnInsert="true"/>
  <Attribute
    Name="RcptNo"
    IsUnique="true"
    Precision="20"
    ColumnName="RCPT_NO"
    SQLType="VARCHAR"
    Type="java.lang.String"
    ColumnType="VARCHAR2"
    TableName="MM$MTL$RCPT"
    RetrievedOnInsert="true">
    <DesignTime>
      <Attr Name="_DisplaySize" Value="20"/>
    </DesignTime>
  </Attribute>
  <Attribute
    Name="RcptDt"
    ColumnName="RCPT_DT"
    SQLType="DATE"
    Type="oracle.jbo.domain.Timestamp"
    ColumnType="DATE"
    TableName="MM$MTL$RCPT"
    RetrievedOnInsert="true"/>
  <Attribute
    Name="RcptSrcType"
    Precision="5"
    Scale="0"
    ColumnName="RCPT_SRC_TYPE"
    SQLType="NUMERIC"
    Type="java.lang.Integer"
    ColumnType="NUMBER"
    TableName="MM$MTL$RCPT"
    RetrievedOnInsert="true"/>
  <Attribute
    Name="RcptStg"
    Precision="5"
    Scale="0"
    ColumnName="RCPT_STG"
    SQLType="NUMERIC"
    Type="java.lang.Integer"
    ColumnType="NUMBER"
    TableName="MM$MTL$RCPT"
    RetrievedOnInsert="true"/>
  <Attribute
    Name="GeDocId"
    Precision="40"
    ColumnName="GE_DOC_ID"
    SQLType="VARCHAR"
    Type="java.lang.String"
    ColumnType="VARCHAR2"
    TableName="MM$MTL$RCPT"
    RetrievedOnInsert="true">
    <DesignTime>
      <Attr Name="_DisplaySize" Value="40"/>
    </DesignTime>
  </Attribute>
  <Attribute
    Name="EoIdSrc"
    Precision="5"
    Scale="0"
    ColumnName="EO_ID_SRC"
    SQLType="NUMERIC"
    Type="java.lang.Integer"
    ColumnType="NUMBER"
    TableName="MM$MTL$RCPT"
    RetrievedOnInsert="true"/>
  <Attribute
    Name="RqmtAreaIdSrc"
    Precision="5"
    Scale="0"
    ColumnName="RQMT_AREA_ID_SRC"
    SQLType="NUMERIC"
    Type="java.lang.Integer"
    ColumnType="NUMBER"
    TableName="MM$MTL$RCPT"
    RetrievedOnInsert="true"/>
  <Attribute
    Name="OrgIdSrc"
    Precision="2"
    ColumnName="ORG_ID_SRC"
    SQLType="VARCHAR"
    Type="java.lang.String"
    ColumnType="VARCHAR2"
    TableName="MM$MTL$RCPT"
    RetrievedOnInsert="true">
    <DesignTime>
      <Attr Name="_DisplaySize" Value="2"/>
    </DesignTime>
  </Attribute>
  <Attribute
    Name="WhIdSrc"
    Precision="20"
    ColumnName="WH_ID_SRC"
    SQLType="VARCHAR"
    Type="java.lang.String"
    ColumnType="VARCHAR2"
    TableName="MM$MTL$RCPT"
    RetrievedOnInsert="true">
    <DesignTime>
      <Attr Name="_DisplaySize" Value="20"/>
    </DesignTime>
  </Attribute>
  <Attribute
    Name="InvoiceNoSrc"
    Precision="100"
    ColumnName="INVOICE_NO_SRC"
    SQLType="VARCHAR"
    Type="java.lang.String"
    ColumnType="VARCHAR2"
    TableName="MM$MTL$RCPT"
    RetrievedOnInsert="true">
    <DesignTime>
      <Attr Name="_DisplaySize" Value="20"/>
    </DesignTime>
  </Attribute>
  <Attribute
    Name="InvoiceDtSrc"
    ColumnName="INVOICE_DT_SRC"
    SQLType="DATE"
    Type="oracle.jbo.domain.Timestamp"
    ColumnType="DATE"
    TableName="MM$MTL$RCPT"
    RetrievedOnInsert="true"/>
  <Attribute
    Name="DnNoSrc"
    Precision="100"
    ColumnName="DN_NO_SRC"
    SQLType="VARCHAR"
    Type="java.lang.String"
    ColumnType="VARCHAR2"
    TableName="MM$MTL$RCPT"
    RetrievedOnInsert="true">
    <DesignTime>
      <Attr Name="_DisplaySize" Value="20"/>
    </DesignTime>
  </Attribute>
  <Attribute
    Name="DnDtSrc"
    ColumnName="DN_DT_SRC"
    SQLType="DATE"
    Type="oracle.jbo.domain.Timestamp"
    ColumnType="DATE"
    TableName="MM$MTL$RCPT"
    RetrievedOnInsert="true"/>
  <Attribute
    Name="EoIdTpt"
    Precision="5"
    Scale="0"
    ColumnName="EO_ID_TPT"
    SQLType="NUMERIC"
    Type="java.lang.Integer"
    ColumnType="NUMBER"
    TableName="MM$MTL$RCPT"
    RetrievedOnInsert="true"/>
  <Attribute
    Name="TptBillNo"
    Precision="30"
    ColumnName="TPT_BILL_NO"
    SQLType="VARCHAR"
    Type="java.lang.String"
    ColumnType="VARCHAR2"
    TableName="MM$MTL$RCPT"
    RetrievedOnInsert="true">
    <DesignTime>
      <Attr Name="_DisplaySize" Value="30"/>
    </DesignTime>
  </Attribute>
  <Attribute
    Name="TptBillDt"
    ColumnName="TPT_BILL_DT"
    SQLType="DATE"
    Type="oracle.jbo.domain.Timestamp"
    ColumnType="DATE"
    TableName="MM$MTL$RCPT"
    RetrievedOnInsert="true"/>
  <Attribute
    Name="VehicleNo"
    Precision="30"
    ColumnName="VEHICLE_NO"
    SQLType="VARCHAR"
    Type="java.lang.String"
    ColumnType="VARCHAR2"
    TableName="MM$MTL$RCPT"
    RetrievedOnInsert="true">
    <DesignTime>
      <Attr Name="_DisplaySize" Value="30"/>
    </DesignTime>
  </Attribute>
  <Attribute
    Name="RcptStat"
    Precision="5"
    Scale="0"
    ColumnName="RCPT_STAT"
    SQLType="NUMERIC"
    Type="java.lang.Integer"
    ColumnType="NUMBER"
    TableName="MM$MTL$RCPT"
    RetrievedOnInsert="true"/>
  <Attribute
    Name="InvoiceReqd"
    Precision="1"
    ColumnName="INVOICE_REQD"
    SQLType="VARCHAR"
    Type="java.lang.String"
    ColumnType="VARCHAR2"
    TableName="MM$MTL$RCPT"
    RetrievedOnInsert="true">
    <DesignTime>
      <Attr Name="_DisplaySize" Value="1"/>
    </DesignTime>
  </Attribute>
  <Attribute
    Name="QcDoneFlg"
    Precision="1"
    ColumnName="QC_DONE_FLG"
    SQLType="VARCHAR"
    Type="java.lang.String"
    ColumnType="VARCHAR2"
    TableName="MM$MTL$RCPT"
    RetrievedOnInsert="true">
    <DesignTime>
      <Attr Name="_DisplaySize" Value="1"/>
    </DesignTime>
  </Attribute>
  <Attribute
    Name="AuthStat"
    Precision="1"
    ColumnName="AUTH_STAT"
    SQLType="VARCHAR"
    Type="java.lang.String"
    ColumnType="VARCHAR2"
    TableName="MM$MTL$RCPT"
    RetrievedOnInsert="true">
    <DesignTime>
      <Attr Name="_DisplaySize" Value="1"/>
    </DesignTime>
  </Attribute>
  <Attribute
    Name="UsrIdCreate"
    Precision="4"
    Scale="0"
    ColumnName="USR_ID_CREATE"
    SQLType="NUMERIC"
    Type="java.lang.Integer"
    ColumnType="NUMBER"
    TableName="MM$MTL$RCPT"
    RetrievedOnInsert="true"/>
  <Attribute
    Name="UsrIdCreateDt"
    ColumnName="USR_ID_CREATE_DT"
    SQLType="DATE"
    Type="oracle.jbo.domain.Timestamp"
    ColumnType="DATE"
    TableName="MM$MTL$RCPT"
    RetrievedOnInsert="true"/>
  <Attribute
    Name="UsrIdMod"
    ColumnName="USR_ID_MOD"
    SQLType="INTEGER"
    Type="java.lang.Integer"
    ColumnType="INTEGER"
    TableName="MM$MTL$RCPT"
    RetrievedOnInsert="true"/>
  <Attribute
    Name="UsrIdModDt"
    ColumnName="USR_ID_MOD_DT"
    SQLType="DATE"
    Type="oracle.jbo.domain.Timestamp"
    ColumnType="DATE"
    TableName="MM$MTL$RCPT"
    RetrievedOnInsert="true"/>
  <Attribute
    Name="AddlAmt"
    ColumnName="ADDL_AMT"
    SQLType="NUMERIC"
    Type="oracle.jbo.domain.Number"
    ColumnType="NUMBER"
    TableName="MM$MTL$RCPT"
    Precision="26"
    Scale="6"
    RetrievedOnInsert="true"/>
  <Attribute
    Name="CurrIdSp"
    ColumnName="CURR_ID_SP"
    SQLType="INTEGER"
    Type="java.lang.Integer"
    ColumnType="INTEGER"
    TableName="MM$MTL$RCPT"
    RetrievedOnInsert="true"/>
  <Attribute
    Name="RmdaStat"
    Precision="1"
    ColumnName="RMDA_STAT"
    SQLType="VARCHAR"
    Type="java.lang.String"
    ColumnType="VARCHAR2"
    TableName="MM$MTL$RCPT"
    RetrievedOnInsert="true">
    <DesignTime>
      <Attr Name="_DisplaySize" Value="1"/>
    </DesignTime>
  </Attribute>
  <Attribute
    Name="Remarks"
    Precision="300"
    ColumnName="REMARKS"
    SQLType="VARCHAR"
    Type="java.lang.String"
    ColumnType="VARCHAR2"
    TableName="MM$MTL$RCPT">
    <DesignTime>
      <Attr Name="_DisplaySize" Value="300"/>
    </DesignTime>
  </Attribute>
  <Attribute
    Name="CoaId"
    ColumnName="COA_ID"
    SQLType="INTEGER"
    Type="java.lang.Integer"
    ColumnType="INTEGER"
    TableName="MM$MTL$RCPT"/>
  <Attribute
    Name="CurrConvFctr"
    ColumnName="CURR_CONV_FCTR"
    SQLType="NUMERIC"
    Type="oracle.jbo.domain.Number"
    ColumnType="NUMBER"
    TableName="MM$MTL$RCPT"/>
  <Attribute
    Name="FileNo"
    Precision="20"
    ColumnName="FILE_NO"
    SQLType="VARCHAR"
    Type="java.lang.String"
    ColumnType="VARCHAR2"
    TableName="MM$MTL$RCPT">
    <DesignTime>
      <Attr Name="_DisplaySize" Value="20"/>
    </DesignTime>
  </Attribute>
  <Attribute
    Name="PrjId"
    IsNotNull="true"
    Precision="40"
    ColumnName="PRJ_ID"
    SQLType="VARCHAR"
    Type="java.lang.String"
    ColumnType="VARCHAR2"
    TableName="MM$MTL$RCPT">
    <DesignTime>
      <Attr Name="_DisplaySize" Value="40"/>
    </DesignTime>
  </Attribute>
  <Attribute
    Name="SuppInvcRcvdOrig"
    Precision="1"
    ColumnName="SUPP_INVC_RCVD_ORIG"
    SQLType="VARCHAR"
    Type="java.lang.String"
    ColumnType="VARCHAR2"
    TableName="MM$MTL$RCPT">
    <DesignTime>
      <Attr Name="_DisplaySize" Value="1"/>
    </DesignTime>
  </Attribute>
  <Attribute
    Name="SuppInvcRcvdTpt"
    Precision="1"
    ColumnName="SUPP_INVC_RCVD_TPT"
    SQLType="VARCHAR"
    Type="java.lang.String"
    ColumnType="VARCHAR2"
    TableName="MM$MTL$RCPT">
    <DesignTime>
      <Attr Name="_DisplaySize" Value="1"/>
    </DesignTime>
  </Attribute>
  <Attribute
    Name="SuppInvcRcvdOrigDt"
    ColumnName="SUPP_INVC_RCVD_ORIG_DT"
    SQLType="DATE"
    Type="oracle.jbo.domain.Timestamp"
    ColumnType="DATE"
    TableName="MM$MTL$RCPT"/>
  <Attribute
    Name="SuppInvcRcvdTptDt"
    ColumnName="SUPP_INVC_RCVD_TPT_DT"
    SQLType="DATE"
    Type="oracle.jbo.domain.Timestamp"
    ColumnType="DATE"
    TableName="MM$MTL$RCPT"/>
  <AccessorAttribute
    Name="MmMtlRcptSrc"
    Association="mmreceiptmtl.model.entities.associations.FkMmMtlRcptSrcAS"
    AssociationEnd="mmreceiptmtl.model.entities.associations.FkMmMtlRcptSrcAS.MmMtlRcptSrc"
    AssociationOtherEnd="mmreceiptmtl.model.entities.associations.FkMmMtlRcptSrcAS.MmMtlRcpt"
    Type="oracle.jbo.RowIterator"
    IsUpdateable="false"/>
  <Key
    Name="PkMmMtlRcpt"
    PrimaryKey="true">
    <DesignTime>
      <Attr Name="_DBObjectName" Value="PK_MM$MTL$RCPT"/>
    </DesignTime>
    <AttrArray Name="Attributes">
      <Item Value="mmreceiptmtl.model.entities.MmMtlRcptEO.CldId"/>
      <Item Value="mmreceiptmtl.model.entities.MmMtlRcptEO.SlocId"/>
      <Item Value="mmreceiptmtl.model.entities.MmMtlRcptEO.OrgId"/>
      <Item Value="mmreceiptmtl.model.entities.MmMtlRcptEO.WhId"/>
      <Item Value="mmreceiptmtl.model.entities.MmMtlRcptEO.DocId"/>
    </AttrArray>
  </Key>
  <Key
    Name="UkMmMtlRcpt">
    <DesignTime>
      <Attr Name="_isUnique" Value="true"/>
      <Attr Name="_DBObjectName" Value="UK_MM$MTL$RCPT"/>
    </DesignTime>
    <AttrArray Name="Attributes">
      <Item Value="mmreceiptmtl.model.entities.MmMtlRcptEO.CldId"/>
      <Item Value="mmreceiptmtl.model.entities.MmMtlRcptEO.SlocId"/>
      <Item Value="mmreceiptmtl.model.entities.MmMtlRcptEO.OrgId"/>
      <Item Value="mmreceiptmtl.model.entities.MmMtlRcptEO.WhId"/>
      <Item Value="mmreceiptmtl.model.entities.MmMtlRcptEO.FyId"/>
      <Item Value="mmreceiptmtl.model.entities.MmMtlRcptEO.RcptNo"/>
    </AttrArray>
  </Key>
  <ResourceBundle>
    <JavaResourceBundle
      MsgBundleClass="mmreceiptmtl.view.bundle.Resource"/>
  </ResourceBundle>
</Entity>
