<?xml version="1.0" encoding="windows-1252" ?>
<!DOCTYPE ViewObject SYSTEM "jbo_03_01.dtd">
<!---->
<ViewObject
  xmlns="http://xmlns.oracle.com/bc4j"
  Name="MMQuotationAnalysisvwVO"
  Version="11.1.2.64.36"
  BindingStyle="OracleName"
  CustomQuery="true"
  PageIterMode="Full"
  UseGlueCode="false">
  <DesignTime>
    <Attr Name="_isExpertMode" Value="true"/>
  </DesignTime>
  <Properties>
    <SchemaBasedProperties>
      <LABEL
        ResId="procurmentprocess.model.views.MMQuotationAnalysisvwVO_LABEL"/>
    </SchemaBasedProperties>
  </Properties>
  <Variable
    Name="BINDCLDID"
    Kind="where"
    Type="java.lang.String"/>
  <Variable
    Name="BINDSLOCID"
    Kind="where"
    Type="java.lang.Integer"/>
  <Variable
    Name="BINDORGID"
    Kind="where"
    Type="java.lang.String"/>
  <Variable
    Name="BindQuotDocId"
    Kind="viewcriteria"
    Type="java.lang.String"/>
  <Variable
    Name="BindRfqDocId"
    Kind="viewcriteria"
    Type="java.lang.String"/>
  <Variable
    Name="BindSupplierId"
    Kind="viewcriteria"
    Type="java.lang.Integer"/>
  <Variable
    Name="BindEvalId"
    Kind="viewcriteria"
    Type="java.lang.String"/>
  <Variable
    Name="BindFrmDate"
    Kind="where"
    Type="oracle.jbo.domain.Date"/>
  <Variable
    Name="BindToDate"
    Kind="where"
    Type="oracle.jbo.domain.Date"/>
  <SQLQuery><![CDATA[SELECT 
    MM$QUOT$ANA$RPT$VW.CLD_ID CLD_ID, 
    MM$QUOT$ANA$RPT$VW.SLOC_ID SLOC_ID, 
    MM$QUOT$ANA$RPT$VW.ORG_ID ORG_ID, 
    MM$QUOT$ANA$RPT$VW.EVAL_ID EVAL_ID, 
    MM$QUOT$ANA$RPT$VW.EVAL_DT EVAL_DT, 
    MM$QUOT$ANA$RPT$VW.RFQ_DOC_ID RFQ_DOC_ID, 
    MM$QUOT$ANA$RPT$VW.RFQ_ID RFQ_ID, 
    MM$QUOT$ANA$RPT$VW.RFQ_DT RFQ_DT, 
    MM$QUOT$ANA$RPT$VW.QUOT_DOC_ID QUOT_DOC_ID, 
    MM$QUOT$ANA$RPT$VW.QUOT_ID QUOT_ID, 
    MM$QUOT$ANA$RPT$VW.QUOT_DT QUOT_DT, 
    MM$QUOT$ANA$RPT$VW.SUPPLIER_ID SUPPLIER_ID, 
    MM$QUOT$ANA$RPT$VW.SUPPLIER_NAME SUPPLIER_NAME, 
    MM$QUOT$ANA$RPT$VW.QUOT_VALUE QUOT_VALUE, 
    MM$QUOT$ANA$RPT$VW.TOTAL_SCORE TOTAL_SCORE 
FROM 
    MM$QUOT$ANA$RPT$VW
where 
MM$QUOT$ANA$RPT$VW.CLD_ID=NVL(:BINDCLDID, MM$QUOT$ANA$RPT$VW.CLD_ID)
AND
MM$QUOT$ANA$RPT$VW.SLOC_ID=NVL(:BINDSLOCID, MM$QUOT$ANA$RPT$VW.SLOC_ID)
AND
MM$QUOT$ANA$RPT$VW.ORG_ID=NVL(:BINDORGID, MM$QUOT$ANA$RPT$VW.ORG_ID)
AND
TO_DATE(MM$QUOT$ANA$RPT$VW.EVAL_DT,'DD-MON-YY')  >=
NVL(TO_DATE(:BindFrmDate,'DD-MON-YY'),TO_DATE(MM$QUOT$ANA$RPT$VW.EVAL_DT,'DD-MON-YY'))
AND TO_DATE(MM$QUOT$ANA$RPT$VW.EVAL_DT,'DD-MON-YY') <=
NVL(TO_DATE(:BindToDate,'DD-MON-YY'),TO_DATE(MM$QUOT$ANA$RPT$VW.EVAL_DT,'DD-MON-YY'))]]></SQLQuery>
  <ViewAttribute
    Name="CldId"
    IsUpdateable="false"
    IsPersistent="false"
    PrecisionRule="true"
    Precision="255"
    Type="java.lang.String"
    ColumnType="VARCHAR2"
    AliasName="CLD_ID"
    Expression="CLD_ID"
    SQLType="VARCHAR">
    <DesignTime>
      <Attr Name="_DisplaySize" Value="4"/>
    </DesignTime>
  </ViewAttribute>
  <ViewAttribute
    Name="SlocId"
    IsUpdateable="false"
    IsPersistent="false"
    PrecisionRule="true"
    Precision="5"
    Scale="0"
    Type="java.lang.Integer"
    ColumnType="NUMBER"
    AliasName="SLOC_ID"
    Expression="SLOC_ID"
    SQLType="NUMERIC"/>
  <ViewAttribute
    Name="OrgId"
    IsUpdateable="false"
    IsPersistent="false"
    PrecisionRule="true"
    Precision="2"
    Type="java.lang.String"
    ColumnType="VARCHAR2"
    AliasName="ORG_ID"
    Expression="ORG_ID"
    SQLType="VARCHAR">
    <DesignTime>
      <Attr Name="_DisplaySize" Value="2"/>
    </DesignTime>
  </ViewAttribute>
  <ViewAttribute
    Name="EvalId"
    IsUpdateable="false"
    IsPersistent="false"
    PrecisionRule="true"
    Precision="40"
    Type="java.lang.String"
    ColumnType="VARCHAR2"
    AliasName="EVAL_ID"
    Expression="EVAL_ID"
    SQLType="VARCHAR">
    <DesignTime>
      <Attr Name="_DisplaySize" Value="40"/>
    </DesignTime>
  </ViewAttribute>
  <ViewAttribute
    Name="EvalDt"
    IsUpdateable="false"
    IsPersistent="false"
    PrecisionRule="true"
    Type="java.sql.Timestamp"
    ColumnType="DATE"
    AliasName="EVAL_DT"
    Expression="EVAL_DT"
    SQLType="DATE"/>
  <ViewAttribute
    Name="RfqDocId"
    IsUpdateable="false"
    IsPersistent="false"
    PrecisionRule="true"
    Precision="40"
    Type="java.lang.String"
    ColumnType="VARCHAR2"
    AliasName="RFQ_DOC_ID"
    Expression="RFQ_DOC_ID"
    SQLType="VARCHAR">
    <DesignTime>
      <Attr Name="_DisplaySize" Value="40"/>
    </DesignTime>
  </ViewAttribute>
  <ViewAttribute
    Name="RfqId"
    IsUpdateable="false"
    IsPersistent="false"
    PrecisionRule="true"
    Precision="20"
    Type="java.lang.String"
    ColumnType="VARCHAR2"
    AliasName="RFQ_ID"
    Expression="RFQ_ID"
    SQLType="VARCHAR">
    <DesignTime>
      <Attr Name="_DisplaySize" Value="20"/>
    </DesignTime>
  </ViewAttribute>
  <ViewAttribute
    Name="RfqDt"
    IsUpdateable="false"
    IsPersistent="false"
    PrecisionRule="true"
    Type="java.sql.Timestamp"
    ColumnType="TIMESTAMP"
    AliasName="RFQ_DT"
    Expression="RFQ_DT"
    SQLType="TIMESTAMP"/>
  <ViewAttribute
    Name="QuotDocId"
    IsUpdateable="false"
    IsPersistent="false"
    PrecisionRule="true"
    Precision="40"
    Type="java.lang.String"
    ColumnType="VARCHAR2"
    AliasName="QUOT_DOC_ID"
    Expression="QUOT_DOC_ID"
    SQLType="VARCHAR">
    <DesignTime>
      <Attr Name="_DisplaySize" Value="40"/>
    </DesignTime>
  </ViewAttribute>
  <ViewAttribute
    Name="QuotId"
    IsUpdateable="false"
    IsPersistent="false"
    PrecisionRule="true"
    Precision="20"
    Type="java.lang.String"
    ColumnType="VARCHAR2"
    AliasName="QUOT_ID"
    Expression="QUOT_ID"
    SQLType="VARCHAR">
    <DesignTime>
      <Attr Name="_DisplaySize" Value="20"/>
    </DesignTime>
  </ViewAttribute>
  <ViewAttribute
    Name="QuotDt"
    IsUpdateable="false"
    IsPersistent="false"
    PrecisionRule="true"
    Type="java.sql.Timestamp"
    ColumnType="DATE"
    AliasName="QUOT_DT"
    Expression="QUOT_DT"
    SQLType="DATE"/>
  <ViewAttribute
    Name="SupplierId"
    IsUpdateable="false"
    IsPersistent="false"
    PrecisionRule="true"
    Type="java.lang.Integer"
    ColumnType="INTEGER"
    AliasName="SUPPLIER_ID"
    Expression="SUPPLIER_ID"
    SQLType="NUMERIC"/>
  <ViewAttribute
    Name="SupplierName"
    IsUpdateable="false"
    IsPersistent="false"
    PrecisionRule="true"
    Precision="250"
    Type="java.lang.String"
    ColumnType="VARCHAR2"
    AliasName="SUPPLIER_NAME"
    Expression="SUPPLIER_NAME"
    SQLType="VARCHAR">
    <DesignTime>
      <Attr Name="_DisplaySize" Value="250"/>
    </DesignTime>
  </ViewAttribute>
  <ViewAttribute
    Name="QuotValue"
    IsUpdateable="false"
    IsPersistent="false"
    PrecisionRule="true"
    Precision="26"
    Scale="6"
    Type="java.math.BigDecimal"
    ColumnType="NUMBER"
    AliasName="QUOT_VALUE"
    Expression="QUOT_VALUE"
    SQLType="NUMERIC"/>
  <ViewAttribute
    Name="TotalScore"
    IsUpdateable="false"
    IsPersistent="false"
    PrecisionRule="true"
    Precision="9"
    Scale="6"
    Type="java.math.BigDecimal"
    ColumnType="NUMBER"
    AliasName="TOTAL_SCORE"
    Expression="TOTAL_SCORE"
    SQLType="NUMERIC"/>
  <ViewCriteria
    Name="MMQuotationAnalysisvwVOCriteria"
    ViewObjectName="procurmentprocess.model.views.MMQuotationAnalysisvwVO"
    Conjunction="AND">
    <Properties>
      <CustomProperties>
        <Property
          Name="displayOperators"
          Value="InAdvancedMode"/>
        <Property
          Name="autoExecute"
          Value="false"/>
        <Property
          Name="allowConjunctionOverride"
          Value="true"/>
        <Property
          Name="showInList"
          Value="true"/>
        <Property
          Name="mode"
          Value="Basic"/>
      </CustomProperties>
    </Properties>
    <ViewCriteriaRow
      Name="MMQuotationAnalysisvwVOCriteria_row_0"
      UpperColumns="1">
      <ViewCriteriaItem
        Name="EvalId"
        ViewAttribute="EvalId"
        Operator="="
        Conjunction="AND"
        Value=":BindEvalId"
        IsBindVarValue="true"
        Required="Optional"/>
      <ViewCriteriaItem
        Name="RfqDocId"
        ViewAttribute="RfqDocId"
        Operator="="
        Conjunction="AND"
        Value=":BindRfqDocId"
        IsBindVarValue="true"
        Required="Optional"/>
      <ViewCriteriaItem
        Name="QuotDocId"
        ViewAttribute="QuotDocId"
        Operator="="
        Conjunction="AND"
        Value=":BindQuotDocId"
        IsBindVarValue="true"
        Required="Optional"/>
      <ViewCriteriaItem
        Name="SupplierId"
        ViewAttribute="SupplierId"
        Operator="="
        Conjunction="AND"
        Value=":BindSupplierId"
        IsBindVarValue="true"
        Required="Optional"/>
    </ViewCriteriaRow>
  </ViewCriteria>
</ViewObject>
