<?xml version="1.0" encoding="windows-1252" ?>
<!DOCTYPE ViewObject SYSTEM "jbo_03_01.dtd">
<!---->
<ViewObject
  xmlns="http://xmlns.oracle.com/bc4j"
  Name="LovCogVO"
  Version="12.1.3.10.8"
  InheritPersonalization="merge"
  BindingStyle="OracleName"
  CustomQuery="true"
  PageIterMode="Full"
  RowClass="schedule6.model.views.LovCogVORowImpl"
  ComponentClass="schedule6.model.views.LovCogVOImpl">
  <DesignTime>
    <Attr Name="_isExpertMode" Value="true"/>
    <Attr Name="_codeGenFlag2" Value="Access|Coll|VarAccess"/>
    <Attr Name="_isCodegen" Value="true"/>
  </DesignTime>
  <Properties>
    <SchemaBasedProperties>
      <LABEL
        ResId="schedule6.model.views.LovCogVO_LABEL"/>
    </SchemaBasedProperties>
  </Properties>
  <Variable
    Name="BindCogId"
    Kind="where"
    Type="java.lang.String">
    <Properties>
      <SchemaBasedProperties>
        <DISPLAYHINT
          Value="Hide"/>
      </SchemaBasedProperties>
    </Properties>
  </Variable>
  <Variable
    Name="BindHoOrgId"
    Kind="where"
    Type="java.lang.String">
    <Properties>
      <SchemaBasedProperties>
        <DISPLAYHINT
          Value="Hide"/>
      </SchemaBasedProperties>
    </Properties>
  </Variable>
  <Variable
    Name="BindCldId"
    Kind="where"
    Type="java.lang.String">
    <Properties>
      <SchemaBasedProperties>
        <DISPLAYHINT
          Value="Hide"/>
      </SchemaBasedProperties>
    </Properties>
  </Variable>
  <Variable
    Name="BindCogName"
    Kind="viewcriteria"
    Type="java.lang.String">
    <Properties>
      <SchemaBasedProperties>
        <LABEL
          ResId="schedule6.model.views.LovCogVO.BindCogName_LABEL"/>
      </SchemaBasedProperties>
    </Properties>
  </Variable>
  <Variable
    Name="BindCogNameVal"
    Kind="viewcriteria"
    Type="java.lang.String"/>
  <SQLQuery><![CDATA[Select cog_id,cog_nm from fin$cog  
where cog_id = nvl(:BindCogId,cog_id)   
and cog_org_id=:BindHoOrgId  
and cog_cld_id=:BindCldId]]></SQLQuery>
  <ViewAttribute
    Name="CogId"
    IsUpdateable="false"
    IsPersistent="false"
    PrecisionRule="true"
    Precision="255"
    Type="java.lang.String"
    ColumnType="VARCHAR2"
    AliasName="COG_ID"
    Expression="COG_ID"
    SQLType="VARCHAR">
    <DesignTime>
      <Attr Name="_DisplaySize" Value="20"/>
    </DesignTime>
  </ViewAttribute>
  <ViewAttribute
    Name="CogNm"
    IsUpdateable="false"
    IsPersistent="false"
    PrecisionRule="true"
    Precision="100"
    Type="java.lang.String"
    ColumnType="VARCHAR2"
    AliasName="COG_NM"
    Expression="COG_NM"
    SQLType="VARCHAR">
    <DesignTime>
      <Attr Name="_DisplaySize" Value="100"/>
    </DesignTime>
    <Properties>
      <SchemaBasedProperties>
        <DISPLAYWIDTH
          Value="30"/>
      </SchemaBasedProperties>
    </Properties>
  </ViewAttribute>
  <ViewCriteria
    Name="LovCogVOCriteria"
    ViewObjectName="schedule6.model.views.LovCogVO"
    Conjunction="AND">
    <Properties>
      <CustomProperties>
        <Property
          Name="displayOperators"
          Value="InAdvancedMode"/>
        <Property
          Name="autoExecute"
          Value="false"/>
        <Property
          Name="allowConjunctionOverride"
          Value="true"/>
        <Property
          Name="showInList"
          Value="true"/>
        <Property
          Name="mode"
          Value="Basic"/>
      </CustomProperties>
    </Properties>
    <ViewCriteriaRow
      Name="LovCogVOCriteria_row_0"
      UpperColumns="1">
      <ViewCriteriaItem
        Name="CogNm"
        ViewAttribute="CogNm"
        Operator="CONTAINS"
        Conjunction="AND"
        Value=":BindCogName"
        IsBindVarValue="true"
        Required="Optional"/>
    </ViewCriteriaRow>
  </ViewCriteria>
  <ViewCriteria
    Name="LovCogVOName"
    ViewObjectName="schedule6.model.views.LovCogVO"
    Conjunction="AND">
    <Properties>
      <CustomProperties>
        <Property
          Name="displayOperators"
          Value="InAdvancedMode"/>
        <Property
          Name="autoExecute"
          Value="false"/>
        <Property
          Name="allowConjunctionOverride"
          Value="true"/>
        <Property
          Name="showInList"
          Value="true"/>
        <Property
          Name="mode"
          Value="Basic"/>
      </CustomProperties>
    </Properties>
    <ViewCriteriaRow
      Name="LovCogVOCriteria1_row_0"
      UpperColumns="1">
      <ViewCriteriaItem
        Name="CogNm"
        ViewAttribute="CogNm"
        Operator="="
        Conjunction="AND"
        Value=":BindCogNameVal"
        IsBindVarValue="true"
        Required="Optional"
        GenerateIsNullClauseForBindVars="true"/>
    </ViewCriteriaRow>
  </ViewCriteria>
  <ResourceBundle>
    <PropertiesBundle
      PropertiesFile="schedule6.model.ModelBundle"/>
  </ResourceBundle>
</ViewObject>
