<?xml version="1.0" encoding="windows-1252" ?>
<!DOCTYPE ViewObject SYSTEM "jbo_03_01.dtd">
<!---->
<ViewObject
  xmlns="http://xmlns.oracle.com/bc4j"
  Name="MmTkrVO"
  Version="11.1.2.64.36"
  BindingStyle="OracleName"
  CustomQuery="true"
  PageIterMode="Full"
  UseGlueCode="false">
  <DesignTime>
    <Attr Name="_isExpertMode" Value="true"/>
  </DesignTime>
  <Properties>
    <SchemaBasedProperties>
      <LABEL
        ResId="TickerApp.model.views.MmTkrVO_LABEL"/>
    </SchemaBasedProperties>
  </Properties>
  <Variable
    Name="BINDCLDID"
    Kind="where"
    Type="java.lang.String"/>
  <Variable
    Name="BINDORGID"
    Kind="where"
    Type="java.lang.String"/>
  <Variable
    Name="BINDSLOCID"
    Kind="where"
    Type="java.lang.Integer"/>
  <Variable
    Name="BindTkrId"
    Kind="viewcriteria"
    Type="java.lang.String"/>
  <Variable
    Name="BindTckrNm"
    Kind="where"
    Type="java.lang.String">
    <Properties>
      <SchemaBasedProperties>
        <DISPLAYHINT
          Value="Hide"/>
      </SchemaBasedProperties>
    </Properties>
  </Variable>
  <ViewAccessor
    Name="LOVDataRangeVO1"
    ViewObjectName="TickerApp.model.views.LOVDataRangeVO"
    RowLevelBinds="true"/>
  <ListBinding
    Name="LOV_DataRangeType"
    ListVOName="LOVDataRangeVO1"
    ListRangeSize="-1"
    NullValueFlag="start"
    NullValueId="${adfBundle['oracle.javatools.resourcebundle.SystemBundle']['NULL_VALUE_RESID']}"
    MRUCount="0">
    <AttrArray Name="AttrNames">
      <Item Value="DataRangeType"/>
    </AttrArray>
    <AttrArray Name="ListAttrNames">
      <Item Value="AttId"/>
    </AttrArray>
    <AttrArray Name="ListDisplayAttrNames">
      <Item Value="AttNm"/>
    </AttrArray>
    <DisplayCriteria/>
  </ListBinding>
  <SQLQuery><![CDATA[SELECT MmTkrEO.ACTV, 
       MmTkrEO.CLD_ID, 
       MmTkrEO.DATA_RANGE_DAYS, 
       MmTkrEO.DATA_RANGE_TYPE, 
       MmTkrEO.ORG_ID, 
       MmTkrEO.SLOC_ID, 
       MmTkrEO.TKR_DESC, 
       MmTkrEO.TKR_ID, 
       MmTkrEO.TKR_NM, 
       MmTkrEO.USR_ID_CREATE, 
       MmTkrEO.USR_ID_CREATE_DT, 
       MmTkrEO.USR_ID_MOD, 
       MmTkrEO.USR_ID_MOD_DT
FROM MM$TKR MmTkrEO
WHERE 
Mmtkreo.Actv='Y'
AND
MmTkrEO.CLD_ID=:BINDCLDID
AND
MmTkrEO.ORG_ID=:BINDORGID
AND
MmTkrEO.SLOC_ID=:BINDSLOCID
AND UPPER(MmTkrEO.TKR_NM) like('%' || UPPER(nvl (:BindTckrNm,MmTkrEO.TKR_NM)||'%'))]]></SQLQuery>
  <EntityUsage
    Name="MmTkrEO"
    Entity="TickerApp.model.entities.MmTkrEO"/>
  <ViewAttribute
    Name="Actv"
    PrecisionRule="true"
    EntityAttrName="Actv"
    EntityUsage="MmTkrEO"
    AliasName="ACTV"/>
  <ViewAttribute
    Name="CldId"
    IsNotNull="true"
    PrecisionRule="true"
    EntityAttrName="CldId"
    EntityUsage="MmTkrEO"
    AliasName="CLD_ID"/>
  <ViewAttribute
    Name="DataRangeDays"
    PrecisionRule="true"
    EntityAttrName="DataRangeDays"
    EntityUsage="MmTkrEO"
    AliasName="DATA_RANGE_DAYS"/>
  <ViewAttribute
    Name="DataRangeType"
    PrecisionRule="true"
    EntityAttrName="DataRangeType"
    EntityUsage="MmTkrEO"
    AliasName="DATA_RANGE_TYPE"
    LOVName="LOV_DataRangeType">
    <Properties>
      <SchemaBasedProperties>
        <CONTROLTYPE
          Value="choice"/>
      </SchemaBasedProperties>
    </Properties>
  </ViewAttribute>
  <ViewAttribute
    Name="OrgId"
    IsNotNull="true"
    PrecisionRule="true"
    EntityAttrName="OrgId"
    EntityUsage="MmTkrEO"
    AliasName="ORG_ID"/>
  <ViewAttribute
    Name="SlocId"
    IsNotNull="true"
    PrecisionRule="true"
    EntityAttrName="SlocId"
    EntityUsage="MmTkrEO"
    AliasName="SLOC_ID"/>
  <ViewAttribute
    Name="TkrDesc"
    PrecisionRule="true"
    EntityAttrName="TkrDesc"
    EntityUsage="MmTkrEO"
    AliasName="TKR_DESC"/>
  <ViewAttribute
    Name="TkrId"
    IsNotNull="true"
    PrecisionRule="true"
    EntityAttrName="TkrId"
    EntityUsage="MmTkrEO"
    AliasName="TKR_ID"/>
  <ViewAttribute
    Name="TkrNm"
    PrecisionRule="true"
    EntityAttrName="TkrNm"
    EntityUsage="MmTkrEO"
    AliasName="TKR_NM"/>
  <ViewAttribute
    Name="UsrIdCreate"
    PrecisionRule="true"
    EntityAttrName="UsrIdCreate"
    EntityUsage="MmTkrEO"
    AliasName="USR_ID_CREATE"/>
  <ViewAttribute
    Name="UsrIdCreateDt"
    PrecisionRule="true"
    EntityAttrName="UsrIdCreateDt"
    EntityUsage="MmTkrEO"
    AliasName="USR_ID_CREATE_DT"
    IsUpdateable="false"/>
  <ViewAttribute
    Name="UsrIdMod"
    PrecisionRule="true"
    EntityAttrName="UsrIdMod"
    EntityUsage="MmTkrEO"
    AliasName="USR_ID_MOD"/>
  <ViewAttribute
    Name="UsrIdModDt"
    PrecisionRule="true"
    EntityAttrName="UsrIdModDt"
    EntityUsage="MmTkrEO"
    AliasName="USR_ID_MOD_DT"
    IsUpdateable="false"/>
  <ViewCriteria
    Name="MmTkrVOCriteria"
    ViewObjectName="TickerApp.model.views.MmTkrVO"
    Conjunction="AND">
    <Properties>
      <CustomProperties>
        <Property
          Name="displayOperators"
          Value="InAdvancedMode"/>
        <Property
          Name="autoExecute"
          Value="false"/>
        <Property
          Name="allowConjunctionOverride"
          Value="true"/>
        <Property
          Name="showInList"
          Value="true"/>
        <Property
          Name="mode"
          Value="Basic"/>
      </CustomProperties>
    </Properties>
    <ViewCriteriaRow
      Name="MmTkrVOCriteria_row_0"
      UpperColumns="1">
      <ViewCriteriaItem
        Name="TkrId"
        ViewAttribute="TkrId"
        Operator="="
        Conjunction="AND"
        Value=":BindTkrId"
        IsBindVarValue="true"
        Required="Optional"/>
    </ViewCriteriaRow>
  </ViewCriteria>
  <ViewLinkAccessor
    Name="MmTkrUsr"
    ViewLink="TickerApp.model.views.links.TkrTOUsrVL"
    Type="oracle.jbo.RowIterator"
    IsUpdateable="false"/>
  <ResourceBundle>
    <PropertiesBundle
      PropertiesFile="TickerApp.model.ModelBundle"/>
  </ResourceBundle>
</ViewObject>
