<?xml version="1.0" encoding="windows-1252" ?>
<!DOCTYPE ViewLink SYSTEM "jbo_03_01.dtd">
<!---->
<ViewLink
  xmlns="http://xmlns.oracle.com/bc4j"
  Name="StructDtlToStructDtlSelfVL"
  Version="12.1.3.10.8"
  InheritPersonalization="merge">
  <Properties>
    <SchemaBasedProperties>
      <LABEL
        ResId="bdgeoprofileapp.model.views.link.StructDtlToStructDtlSelfVL_LABEL"/>
    </SchemaBasedProperties>
  </Properties>
  <ViewLinkDefEnd
    Name="CldIdStructDetail"
    Cardinality="1"
    Source="true"
    Owner="bdgeoprofileapp.model.views.StructDetailVO">
    <DesignTime>
      <Attr Name="_finderName" Value="CldIdStructDetail"/>
      <Attr Name="_isUpdateable" Value="true"/>
    </DesignTime>
    <AttrArray Name="Attributes">
      <Item Value="bdgeoprofileapp.model.views.StructDetailVO.CldId"/>
      <Item Value="bdgeoprofileapp.model.views.StructDetailVO.SlocId"/>
      <Item Value="bdgeoprofileapp.model.views.StructDetailVO.OrgId"/>
      <Item Value="bdgeoprofileapp.model.views.StructDetailVO.ParamId"/>
      <Item Value="bdgeoprofileapp.model.views.StructDetailVO.DocStruct"/>
    </AttrArray>
  </ViewLinkDefEnd>
  <ViewLinkDefEnd
    Name="CldIdStructDetail_2"
    Cardinality="-1"
    Owner="bdgeoprofileapp.model.views.StructDetailVO">
    <DesignTime>
      <Attr Name="_finderName" Value="CldIdStructDetail_2"/>
      <Attr Name="_isUpdateable" Value="true"/>
    </DesignTime>
    <AttrArray Name="Attributes">
      <Item Value="bdgeoprofileapp.model.views.StructDetailVO.CldId"/>
      <Item Value="bdgeoprofileapp.model.views.StructDetailVO.SlocId"/>
      <Item Value="bdgeoprofileapp.model.views.StructDetailVO.OrgId"/>
      <Item Value="bdgeoprofileapp.model.views.StructDetailVO.DependStructVal"/>
      <Item Value="bdgeoprofileapp.model.views.StructDetailVO.DocStructDepd"/>
    </AttrArray>
  </ViewLinkDefEnd>
  <ResourceBundle>
    <PropertiesBundle
      PropertiesFile="bdgeoprofileapp.model.ModelBundle"/>
  </ResourceBundle>
</ViewLink>
