<?xml version="1.0" encoding="UTF-8" ?>
<pageDefinition xmlns="http://xmlns.oracle.com/adfm/uimodel" version="11.1.2.64.36" id="SrchStockAdjtPagePageDef"
                Package="mmstockadjustment.view.pageDefs">
  <parameters/>
  <executables>
    <variableIterator id="variables"/>
    <iterator Binds="transSrch1" RangeSize="25" DataControl="MMStockAdjustmentAMDataControl" id="transSrch1Iterator"/>
    <iterator Binds="STKADJT1" RangeSize="25" DataControl="MMStockAdjustmentAMDataControl" id="STKADJT1Iterator"/>
  </executables>
  <bindings>
    <attributeValues IterBinding="transSrch1Iterator" id="fromDate">
      <AttrNames>
        <Item Value="fromDate"/>
      </AttrNames>
    </attributeValues>
    <attributeValues IterBinding="transSrch1Iterator" id="toDate">
      <AttrNames>
        <Item Value="toDate"/>
      </AttrNames>
    </attributeValues>
    <tree IterBinding="STKADJT1Iterator" id="STKADJT1">
      <nodeDefinition DefName="mmstockadjustment.model.view.STKADJTVO" Name="STKADJT10">
        <AttrNames>
          <Item Value="StkAdjtNo"/>
          <Item Value="StkAdjtStat"/>
          <Item Value="LovSwitcher"/>
          <Item Value="StkAdjtDt"/>
          <Item Value="RefDocId"/>
        </AttrNames>
      </nodeDefinition>
    </tree>
    <list IterBinding="STKADJT1Iterator" StaticList="false" Uses="LOV_StkAdjtStat" id="StkAdjtStat"
          DTSupportsMRU="true" SelectItemValueMode="ListObject"/>
    <methodAction id="searchAction" InstanceName="data.MMStockAdjustmentAMDataControl.dataProvider"
                  DataControl="MMStockAdjustmentAMDataControl" RequiresUpdateModel="true" Action="invokeMethod"
                  MethodName="searchAction" IsViewObjectMethod="false">
      <NamedData NDName="stkAdjtNo" NDType="java.lang.String"/>
      <NamedData NDName="frmDate" NDType="oracle.jbo.domain.Timestamp"/>
      <NamedData NDName="toDate" NDType="oracle.jbo.domain.Timestamp"/>
      <NamedData NDName="stckStat" NDType="java.lang.Integer"/>
    </methodAction>
    <listOfValues StaticList="false" IterBinding="transSrch1Iterator" Uses="LOV_stkAdjtNo" id="stkAdjtNo1"/>
    <list IterBinding="transSrch1Iterator" StaticList="false" Uses="LOV_stckStat" id="stckStat" DTSupportsMRU="true"
          SelectItemValueMode="ListObject"/>
    <methodAction id="defaultSearchAction" InstanceName="data.MMStockAdjustmentAMDataControl.dataProvider"
                  DataControl="MMStockAdjustmentAMDataControl" RequiresUpdateModel="true" Action="invokeMethod"
                  MethodName="defaultSearchAction" IsViewObjectMethod="false"
                  ReturnName="data.MMStockAdjustmentAMDataControl.methodResults.defaultSearchAction_MMStockAdjustmentAMDataControl_dataProvider_defaultSearchAction_result"/>
    <methodAction id="resetAction" InstanceName="data.MMStockAdjustmentAMDataControl.dataProvider"
                  DataControl="MMStockAdjustmentAMDataControl" RequiresUpdateModel="true" Action="invokeMethod"
                  MethodName="resetAction" IsViewObjectMethod="false"/>
    <attributeValues IterBinding="STKADJT1Iterator" id="DocId">
      <AttrNames>
        <Item Value="DocId"/>
      </AttrNames>
    </attributeValues>
  </bindings>
</pageDefinition>
