<?xml version="1.0" encoding="windows-1252" ?>
<!DOCTYPE ViewObject SYSTEM "jbo_03_01.dtd">
<!---->
<ViewObject
  xmlns="http://xmlns.oracle.com/bc4j"
  Name="FASearchVO"
  Version="12.1.3.10.8"
  InheritPersonalization="merge"
  BindingStyle="OracleName"
  CustomQuery="true"
  PageIterMode="Full"
  RowClass="fasearchapp.model.views.FASearchVORowImpl">
  <DesignTime>
    <Attr Name="_isExpertMode" Value="true"/>
    <Attr Name="_codeGenFlag2" Value="Access"/>
    <Attr Name="_isCodegen" Value="true"/>
  </DesignTime>
  <Properties>
    <SchemaBasedProperties>
      <LABEL
        ResId="fasearchapp.model.views.FASearchVO_LABEL"/>
    </SchemaBasedProperties>
  </Properties>
  <ViewAccessor
    Name="LovFyDescVO"
    ViewObjectName="fasearchapp.model.views.LovFyDescVO"
    RowLevelBinds="true">
    <ParameterMap>
      <PIMap Variable="BindOrgId">
        <TransientExpression
          trustMode="untrusted"><![CDATA[TransOrgId]]></TransientExpression>
      </PIMap>
      <PIMap Variable="BindSlocId">
        <TransientExpression
          trustMode="untrusted"><![CDATA[TransSlocId]]></TransientExpression>
      </PIMap>
    </ParameterMap>
  </ViewAccessor>
  <ViewAccessor
    Name="LovLawTypVO"
    ViewObjectName="fasearchapp.model.views.LovLawTypVO"
    RowLevelBinds="true"/>
  <ViewAccessor
    Name="LovPeriodVO"
    ViewObjectName="fasearchapp.model.views.LovPeriodVO"
    RowLevelBinds="true">
    <ParameterMap>
      <PIMap Variable="BIndCldId">
        <TransientExpression
          trustMode="untrusted"><![CDATA[TransCldId]]></TransientExpression>
      </PIMap>
      <PIMap Variable="BindOrgFyId">
        <TransientExpression
          trustMode="untrusted"><![CDATA[TransFyId]]></TransientExpression>
      </PIMap>
      <PIMap Variable="BindOrgId">
        <TransientExpression
          trustMode="untrusted"><![CDATA[TransOrgId]]></TransientExpression>
      </PIMap>
    </ParameterMap>
  </ViewAccessor>
  <ViewAccessor
    Name="LovItmGroupVO"
    ViewObjectName="fasearchapp.model.views.LovItmGroupVO"
    RowLevelBinds="true">
    <ParameterMap>
      <PIMap Variable="BindCldId">
        <TransientExpression
          trustMode="untrusted"><![CDATA[TransCldId]]></TransientExpression>
      </PIMap>
      <PIMap Variable="BindHoOrgId">
        <TransientExpression
          trustMode="untrusted"><![CDATA[TransHoOrgId]]></TransientExpression>
      </PIMap>
      <PIMap Variable="BindOrgId">
        <TransientExpression
          trustMode="untrusted"><![CDATA[TransOrgId]]></TransientExpression>
      </PIMap>
      <PIMap Variable="BindSlocId">
        <TransientExpression
          trustMode="untrusted"><![CDATA[TransSlocId]]></TransientExpression>
      </PIMap>
    </ParameterMap>
  </ViewAccessor>
  <ViewAccessor
    Name="LovItmVO"
    ViewObjectName="fasearchapp.model.views.LovItmVO"
    RowLevelBinds="true">
    <ParameterMap>
      <PIMap Variable="BindCldId">
        <TransientExpression
          trustMode="untrusted"><![CDATA[TransCldId]]></TransientExpression>
      </PIMap>
      <PIMap Variable="BindGrpId">
        <TransientExpression
          trustMode="untrusted"><![CDATA[TransitmGrpId]]></TransientExpression>
      </PIMap>
      <PIMap Variable="BindHoOrgId">
        <TransientExpression
          trustMode="untrusted"><![CDATA[TransHoOrgId]]></TransientExpression>
      </PIMap>
      <PIMap Variable="BindOrgId">
        <TransientExpression
          trustMode="untrusted"><![CDATA[TransOrgId]]></TransientExpression>
      </PIMap>
      <PIMap Variable="BindSlocId">
        <TransientExpression
          trustMode="untrusted"><![CDATA[TransSlocId]]></TransientExpression>
      </PIMap>
    </ParameterMap>
  </ViewAccessor>
  <ViewAccessor
    Name="LovVouDispIdVO"
    ViewObjectName="fasearchapp.model.views.LovVouDispIdVO"
    RowLevelBinds="true">
    <ParameterMap>
      <PIMap Variable="BindCldId">
        <TransientExpression
          trustMode="untrusted"><![CDATA[TransCldId]]></TransientExpression>
      </PIMap>
      <PIMap Variable="BindOrgId">
        <TransientExpression
          trustMode="untrusted"><![CDATA[TransOrgId]]></TransientExpression>
      </PIMap>
      <PIMap Variable="BindSlocId">
        <TransientExpression
          trustMode="untrusted"><![CDATA[TransSlocId]]></TransientExpression>
      </PIMap>
    </ParameterMap>
  </ViewAccessor>
  <ViewAccessor
    Name="LovDocSourceVO"
    ViewObjectName="fasearchapp.model.views.LovDocSourceVO"
    RowLevelBinds="true"/>
  <ViewAccessor
    Name="LovDepVouIdVO"
    ViewObjectName="fasearchapp.model.views.LovDepVouId"
    RowLevelBinds="true">
    <ParameterMap>
      <PIMap Variable="BindCldId">
        <TransientExpression
          trustMode="untrusted"><![CDATA[TransCldId]]></TransientExpression>
      </PIMap>
      <PIMap Variable="BindHoorgId">
        <TransientExpression
          trustMode="untrusted"><![CDATA[TransHoOrgId]]></TransientExpression>
      </PIMap>
      <PIMap Variable="BindOrgId">
        <TransientExpression
          trustMode="untrusted"><![CDATA[TransOrgId]]></TransientExpression>
      </PIMap>
      <PIMap Variable="BindSlocId">
        <TransientExpression
          trustMode="untrusted"><![CDATA[TransSlocId]]></TransientExpression>
      </PIMap>
    </ParameterMap>
  </ViewAccessor>
  <ViewAccessor
    Name="LovFaDispIdVO1"
    ViewObjectName="fasearchapp.model.views.LovFaDispIdVO"
    RowLevelBinds="true">
    <ParameterMap>
      <PIMap Variable="BindCldId">
        <TransientExpression
          trustMode="untrusted"><![CDATA[TransCldId]]></TransientExpression>
      </PIMap>
      <PIMap Variable="BindHoOrgId">
        <TransientExpression
          trustMode="untrusted"><![CDATA[TransHoOrgId]]></TransientExpression>
      </PIMap>
      <PIMap Variable="BindOrgId">
        <TransientExpression
          trustMode="untrusted"><![CDATA[TransOrgId]]></TransientExpression>
      </PIMap>
      <PIMap Variable="BindSlocId">
        <TransientExpression
          trustMode="untrusted"><![CDATA[TransSlocId]]></TransientExpression>
      </PIMap>
    </ParameterMap>
  </ViewAccessor>
  <ListBinding
    Name="LOV_TransFyId"
    ListVOName="LovFyDescVO"
    ListRangeSize="-1"
    NullValueFlag="start"
    NullValueId="${adfBundle['oracle.javatools.resourcebundle.SystemBundle']['NULL_VALUE_RESID']}"
    MRUCount="0">
    <AttrArray Name="AttrNames">
      <Item Value="TransFyId"/>
    </AttrArray>
    <AttrArray Name="AttrExpressions"/>
    <AttrArray Name="ListAttrNames">
      <Item Value="OrgFyId"/>
    </AttrArray>
    <AttrArray Name="ListDisplayAttrNames">
      <Item Value="FyDesc"/>
    </AttrArray>
    <DisplayCriteria/>
  </ListBinding>
  <ListBinding
    Name="LOV_TransLawType"
    ListVOName="LovLawTypVO"
    ListRangeSize="-1"
    NullValueFlag="none"
    MRUCount="0">
    <AttrArray Name="AttrNames">
      <Item Value="TransLawType"/>
    </AttrArray>
    <AttrArray Name="AttrExpressions"/>
    <AttrArray Name="ListAttrNames">
      <Item Value="LawId"/>
    </AttrArray>
    <AttrArray Name="ListDisplayAttrNames">
      <Item Value="LawTyp"/>
    </AttrArray>
    <DisplayCriteria/>
  </ListBinding>
  <ListBinding
    Name="LOV_TransPeriodId"
    ListVOName="LovPeriodVO"
    ListRangeSize="-1"
    NullValueFlag="start"
    NullValueId="${adfBundle['oracle.javatools.resourcebundle.SystemBundle']['NULL_VALUE_RESID']}"
    MRUCount="0">
    <AttrArray Name="AttrNames">
      <Item Value="TransPeriodId"/>
    </AttrArray>
    <AttrArray Name="AttrExpressions"/>
    <AttrArray Name="ListAttrNames">
      <Item Value="PrdId"/>
    </AttrArray>
    <AttrArray Name="ListDisplayAttrNames">
      <Item Value="Prd"/>
    </AttrArray>
    <DisplayCriteria/>
  </ListBinding>
  <ListBinding
    Name="LOV_TransItmGrpDesc"
    ListVOName="LovItmGroupVO"
    ListRangeSize="-1"
    NullValueFlag="none"
    MRUCount="0"
    ComboRowCountHint="10">
    <AttrArray Name="AttrNames">
      <Item Value="TransItmGrpDesc"/>
    </AttrArray>
    <AttrArray Name="AttrExpressions"/>
    <AttrArray Name="DerivedAttrNames">
      <Item Value="TransitmGrpId"/>
    </AttrArray>
    <AttrArray Name="ListAttrNames">
      <Item Value="GroupName"/>
      <Item Value="GrpId"/>
    </AttrArray>
    <AttrArray Name="ListDisplayAttrNames">
      <Item Value="GroupName"/>
    </AttrArray>
    <DisplayCriteria/>
  </ListBinding>
  <ListBinding
    Name="LOV_transItmDesc"
    ListVOName="LovItmVO"
    ListRangeSize="-1"
    ComboRowCountHint="10"
    NullValueFlag="none"
    MRUCount="0">
    <AttrArray Name="AttrNames">
      <Item Value="transItmDesc"/>
    </AttrArray>
    <AttrArray Name="AttrExpressions"/>
    <AttrArray Name="DerivedAttrNames">
      <Item Value="TransItmId"/>
    </AttrArray>
    <AttrArray Name="ListAttrNames">
      <Item Value="Itemdesc"/>
      <Item Value="ItmId"/>
    </AttrArray>
    <AttrArray Name="ListDisplayAttrNames">
      <Item Value="Itemdesc"/>
    </AttrArray>
    <DisplayCriteria/>
  </ListBinding>
  <ListBinding
    Name="LOV_transPurVouDisp"
    ListVOName="LovVouDispIdVO"
    ListRangeSize="-1"
    ComboRowCountHint="10"
    NullValueFlag="none"
    MRUCount="0">
    <AttrArray Name="AttrNames">
      <Item Value="transPurVouDisp"/>
    </AttrArray>
    <AttrArray Name="AttrExpressions"/>
    <AttrArray Name="DerivedAttrNames">
      <Item Value="TransPurVouId"/>
    </AttrArray>
    <AttrArray Name="ListAttrNames">
      <Item Value="InvcNo"/>
      <Item Value="DocId"/>
    </AttrArray>
    <AttrArray Name="ListDisplayAttrNames">
      <Item Value="InvcNo"/>
    </AttrArray>
    <DisplayCriteria/>
  </ListBinding>
  <ListBinding
    Name="LOV_TransDocSrc"
    ListVOName="LovDocSourceVO"
    ListRangeSize="-1"
    NullValueFlag="start"
    NullValueId="${adfBundle['oracle.javatools.resourcebundle.SystemBundle']['NULL_VALUE_RESID']}"
    MRUCount="0">
    <AttrArray Name="AttrNames">
      <Item Value="TransDocSrc"/>
    </AttrArray>
    <AttrArray Name="AttrExpressions"/>
    <AttrArray Name="ListAttrNames">
      <Item Value="Id"/>
    </AttrArray>
    <AttrArray Name="ListDisplayAttrNames">
      <Item Value="Vname"/>
    </AttrArray>
    <DisplayCriteria/>
  </ListBinding>
  <ListBinding
    Name="LOV_TransDepVouDisp"
    ListVOName="LovDepVouIdVO"
    ListRangeSize="-1"
    ComboRowCountHint="10"
    NullValueFlag="start"
    NullValueId="${adfBundle['oracle.javatools.resourcebundle.SystemBundle']['NULL_VALUE_RESID']}"
    MRUCount="0">
    <AttrArray Name="AttrNames">
      <Item Value="TransDepVouDisp"/>
    </AttrArray>
    <AttrArray Name="AttrExpressions"/>
    <AttrArray Name="DerivedAttrNames">
      <Item Value="TranDepVouId"/>
    </AttrArray>
    <AttrArray Name="ListAttrNames">
      <Item Value="DepExeDispId"/>
      <Item Value="DepExeId"/>
    </AttrArray>
    <AttrArray Name="ListDisplayAttrNames">
      <Item Value="DepExeDispId"/>
    </AttrArray>
    <DisplayCriteria/>
  </ListBinding>
  <ListBinding
    Name="LOV_TransRegisterFaDispId"
    ListVOName="LovFaDispIdVO1"
    ListRangeSize="-1"
    NullValueFlag="start"
    NullValueId="${adfBundle['oracle.javatools.resourcebundle.SystemBundle']['NULL_VALUE_RESID']}"
    MRUCount="0">
    <AttrArray Name="AttrNames">
      <Item Value="TransRegisterFaDispId"/>
    </AttrArray>
    <AttrArray Name="AttrExpressions"/>
    <AttrArray Name="ListAttrNames">
      <Item Value="DocIdDisp"/>
    </AttrArray>
    <AttrArray Name="ListDisplayAttrNames">
      <Item Value="DocIdDisp"/>
    </AttrArray>
    <DisplayCriteria/>
  </ListBinding>
  <SQLQuery><![CDATA[select * from dual]]></SQLQuery>
  <ViewAttribute
    Name="TransFyId"
    IsSelected="false"
    IsPersistent="false"
    PrecisionRule="true"
    Type="java.lang.Integer"
    ColumnType="INTEGER"
    AliasName="VIEW_ATTR"
    SQLType="INTEGER"
    LOVName="LOV_TransFyId">
    <Properties>
      <SchemaBasedProperties>
        <CONTROLTYPE
          Value="choice"/>
      </SchemaBasedProperties>
    </Properties>
  </ViewAttribute>
  <ViewAttribute
    Name="TransItmGrpDesc"
    IsSelected="false"
    IsPersistent="false"
    PrecisionRule="true"
    Precision="255"
    Type="java.lang.String"
    ColumnType="VARCHAR2"
    AliasName="VIEW_ATTR"
    SQLType="VARCHAR"
    LOVName="LOV_TransItmGrpDesc">
    <Properties>
      <SchemaBasedProperties>
        <CONTROLTYPE
          Value="input_text_lov"/>
      </SchemaBasedProperties>
    </Properties>
  </ViewAttribute>
  <ViewAttribute
    Name="TransitmGrpId"
    IsSelected="false"
    IsPersistent="false"
    PrecisionRule="true"
    Precision="255"
    Type="java.lang.String"
    ColumnType="VARCHAR2"
    AliasName="VIEW_ATTR"
    SQLType="VARCHAR"/>
  <ViewAttribute
    Name="TransItmId"
    IsSelected="false"
    IsPersistent="false"
    PrecisionRule="true"
    Precision="255"
    Type="java.lang.String"
    ColumnType="VARCHAR2"
    AliasName="VIEW_ATTR"
    SQLType="VARCHAR"/>
  <ViewAttribute
    Name="transItmDesc"
    IsSelected="false"
    IsPersistent="false"
    PrecisionRule="true"
    Precision="255"
    Type="java.lang.String"
    ColumnType="VARCHAR2"
    AliasName="VIEW_ATTR"
    SQLType="VARCHAR"
    LOVName="LOV_transItmDesc">
    <Properties>
      <SchemaBasedProperties>
        <CONTROLTYPE
          Value="input_text_lov"/>
      </SchemaBasedProperties>
    </Properties>
  </ViewAttribute>
  <ViewAttribute
    Name="TransPurVouId"
    IsSelected="false"
    IsPersistent="false"
    PrecisionRule="true"
    Precision="255"
    Type="java.lang.String"
    ColumnType="VARCHAR2"
    AliasName="VIEW_ATTR"
    SQLType="VARCHAR"/>
  <ViewAttribute
    Name="transPurVouDisp"
    IsSelected="false"
    IsPersistent="false"
    PrecisionRule="true"
    Precision="255"
    Type="java.lang.String"
    ColumnType="VARCHAR2"
    AliasName="VIEW_ATTR"
    SQLType="VARCHAR"
    LOVName="LOV_transPurVouDisp">
    <Properties>
      <SchemaBasedProperties>
        <CONTROLTYPE
          Value="input_text_lov"/>
      </SchemaBasedProperties>
    </Properties>
  </ViewAttribute>
  <ViewAttribute
    Name="TransDocSrc"
    IsSelected="false"
    IsPersistent="false"
    PrecisionRule="true"
    Precision="255"
    Type="java.lang.Integer"
    ColumnType="VARCHAR2"
    AliasName="VIEW_ATTR"
    SQLType="INTEGER"
    LOVName="LOV_TransDocSrc">
    <Properties>
      <SchemaBasedProperties>
        <CONTROLTYPE
          Value="choice"/>
      </SchemaBasedProperties>
    </Properties>
  </ViewAttribute>
  <ViewAttribute
    Name="TransPeriodId"
    IsSelected="false"
    IsPersistent="false"
    PrecisionRule="true"
    Precision="255"
    Type="java.lang.Integer"
    ColumnType="VARCHAR2"
    AliasName="VIEW_ATTR"
    SQLType="INTEGER"
    LOVName="LOV_TransPeriodId">
    <Properties>
      <SchemaBasedProperties>
        <CONTROLTYPE
          Value="choice"/>
      </SchemaBasedProperties>
    </Properties>
  </ViewAttribute>
  <ViewAttribute
    Name="TransFromDt"
    IsSelected="false"
    IsPersistent="false"
    PrecisionRule="true"
    Type="oracle.jbo.domain.Date"
    ColumnType="DATE"
    AliasName="VIEW_ATTR"
    SQLType="DATE"/>
  <ViewAttribute
    Name="TransEndDt"
    IsSelected="false"
    IsPersistent="false"
    PrecisionRule="true"
    Type="oracle.jbo.domain.Date"
    ColumnType="DATE"
    AliasName="VIEW_ATTR"
    SQLType="DATE"/>
  <ViewAttribute
    Name="TransLawType"
    IsSelected="false"
    IsPersistent="false"
    PrecisionRule="true"
    Precision="255"
    Type="java.lang.String"
    ColumnType="VARCHAR2"
    AliasName="VIEW_ATTR"
    SQLType="VARCHAR"
    LOVName="LOV_TransLawType">
    <Properties>
      <SchemaBasedProperties>
        <CONTROLTYPE
          Value="choice"/>
      </SchemaBasedProperties>
    </Properties>
  </ViewAttribute>
  <ViewAttribute
    Name="TransCldId"
    IsSelected="false"
    IsPersistent="false"
    PrecisionRule="true"
    Precision="255"
    Type="java.lang.String"
    ColumnType="VARCHAR2"
    AliasName="VIEW_ATTR"
    SQLType="VARCHAR"/>
  <ViewAttribute
    Name="TransSlocId"
    IsSelected="false"
    IsPersistent="false"
    PrecisionRule="true"
    Type="java.lang.Integer"
    ColumnType="INTEGER"
    AliasName="VIEW_ATTR"
    SQLType="INTEGER"/>
  <ViewAttribute
    Name="TransOrgId"
    IsSelected="false"
    IsPersistent="false"
    PrecisionRule="true"
    Precision="255"
    Type="java.lang.String"
    ColumnType="VARCHAR2"
    AliasName="VIEW_ATTR"
    SQLType="VARCHAR"/>
  <ViewAttribute
    Name="TransHoOrgId"
    IsSelected="false"
    IsPersistent="false"
    PrecisionRule="true"
    Precision="255"
    Type="java.lang.String"
    ColumnType="VARCHAR2"
    AliasName="VIEW_ATTR"
    SQLType="VARCHAR"/>
  <ViewAttribute
    Name="TranDepVouId"
    IsSelected="false"
    IsPersistent="false"
    PrecisionRule="true"
    Precision="255"
    Type="java.lang.String"
    ColumnType="VARCHAR2"
    AliasName="VIEW_ATTR"
    SQLType="VARCHAR"/>
  <ViewAttribute
    Name="TransDepVouDisp"
    IsSelected="false"
    IsPersistent="false"
    PrecisionRule="true"
    Precision="255"
    Type="java.lang.String"
    ColumnType="VARCHAR2"
    AliasName="VIEW_ATTR"
    SQLType="VARCHAR"
    LOVName="LOV_TransDepVouDisp">
    <Properties>
      <SchemaBasedProperties>
        <CONTROLTYPE
          Value="input_text_lov"/>
      </SchemaBasedProperties>
    </Properties>
  </ViewAttribute>
  <ViewAttribute
    Name="TransRegisterFaDispId"
    IsSelected="false"
    IsPersistent="false"
    PrecisionRule="true"
    Precision="255"
    Type="java.lang.String"
    ColumnType="VARCHAR2"
    AliasName="VIEW_ATTR"
    SQLType="VARCHAR"
    LOVName="LOV_TransRegisterFaDispId">
    <Properties>
      <SchemaBasedProperties>
        <CONTROLTYPE
          Value="choice"/>
      </SchemaBasedProperties>
    </Properties>
  </ViewAttribute>
  <ResourceBundle>
    <PropertiesBundle
      PropertiesFile="fasearchapp.model.ModelBundle"/>
  </ResourceBundle>
</ViewObject>
