<?xml version="1.0" encoding="windows-1252" ?>
<!DOCTYPE ViewObject SYSTEM "jbo_03_01.dtd">
<!---->
<ViewObject
  xmlns="http://xmlns.oracle.com/bc4j"
  Name="MmIpoIdfAttchVO"
  Version="12.1.3.10.8"
  InheritPersonalization="merge"
  SelectListFlags="1"
  FromListFlags="1"
  WhereFlags="1"
  BindingStyle="OracleName"
  CustomQuery="false"
  SelectAllAttributes="false"
  PageIterMode="Full"
  RowClass="mmidfapp.model.views.MmIpoIdfAttchVORowImpl">
  <DesignTime>
    <Attr Name="_codeGenFlag2" Value="Access"/>
    <Attr Name="_isCodegen" Value="true"/>
  </DesignTime>
  <Properties>
    <SchemaBasedProperties>
      <LABEL
        ResId="mmidfapp.model.views.MmIpoIdfAttchVO_LABEL"/>
    </SchemaBasedProperties>
  </Properties>
  <EntityUsage
    Name="MmIpoIdfAttchEO"
    Entity="mmidfapp.model.entities.MmIpoIdfAttchEO"/>
  <ViewAttribute
    Name="AttchFl"
    IsQueriable="false"
    PrecisionRule="true"
    EntityAttrName="AttchFl"
    EntityUsage="MmIpoIdfAttchEO"
    AliasName="ATTCH_FL"/>
  <ViewAttribute
    Name="CldId"
    IsNotNull="true"
    PrecisionRule="true"
    EntityAttrName="CldId"
    EntityUsage="MmIpoIdfAttchEO"
    AliasName="CLD_ID"/>
  <ViewAttribute
    Name="DispFlNm"
    PrecisionRule="true"
    EntityAttrName="DispFlNm"
    EntityUsage="MmIpoIdfAttchEO"
    AliasName="DISP_FL_NM"/>
  <ViewAttribute
    Name="DocId"
    IsNotNull="true"
    PrecisionRule="true"
    EntityAttrName="DocId"
    EntityUsage="MmIpoIdfAttchEO"
    AliasName="DOC_ID"/>
  <ViewAttribute
    Name="FlExtn"
    PrecisionRule="true"
    EntityAttrName="FlExtn"
    EntityUsage="MmIpoIdfAttchEO"
    AliasName="FL_EXTN"/>
  <ViewAttribute
    Name="FlNm"
    IsNotNull="true"
    PrecisionRule="true"
    EntityAttrName="FlNm"
    EntityUsage="MmIpoIdfAttchEO"
    AliasName="FL_NM"/>
  <ViewAttribute
    Name="FlPath"
    PrecisionRule="true"
    EntityAttrName="FlPath"
    EntityUsage="MmIpoIdfAttchEO"
    AliasName="FL_PATH"/>
  <ViewAttribute
    Name="HoOrgId"
    IsNotNull="true"
    PrecisionRule="true"
    EntityAttrName="HoOrgId"
    EntityUsage="MmIpoIdfAttchEO"
    AliasName="HO_ORG_ID"/>
  <ViewAttribute
    Name="OrgId"
    IsNotNull="true"
    PrecisionRule="true"
    EntityAttrName="OrgId"
    EntityUsage="MmIpoIdfAttchEO"
    AliasName="ORG_ID"/>
  <ViewAttribute
    Name="Remarks"
    PrecisionRule="true"
    EntityAttrName="Remarks"
    EntityUsage="MmIpoIdfAttchEO"
    AliasName="REMARKS"/>
  <ViewAttribute
    Name="SlocId"
    IsNotNull="true"
    PrecisionRule="true"
    EntityAttrName="SlocId"
    EntityUsage="MmIpoIdfAttchEO"
    AliasName="SLOC_ID"/>
  <ViewAttribute
    Name="TransKey"
    IsSelected="false"
    IsPersistent="false"
    PrecisionRule="true"
    Precision="255"
    Type="java.lang.String"
    ColumnType="VARCHAR2"
    AliasName="VIEW_ATTR"
    SQLType="VARCHAR"/>
  <ResourceBundle>
    <PropertiesBundle
      PropertiesFile="mmidfapp.model.ModelBundle"/>
  </ResourceBundle>
</ViewObject>
