<?xml version="1.0" encoding="windows-1252" ?>
<!DOCTYPE ViewObject SYSTEM "jbo_03_01.dtd">
<!---->
<ViewObject
  xmlns="http://xmlns.oracle.com/bc4j"
  Name="MmShpAdvc1VO"
  Version="12.1.3.10.8"
  InheritPersonalization="merge"
  BindingStyle="OracleName"
  CustomQuery="true"
  FetchMode="FETCH_AS_NEEDED"
  PageIterMode="Full">
  <DesignTime>
    <Attr Name="_isExpertMode" Value="true"/>
  </DesignTime>
  <SQLQuery><![CDATA[SELECT MmShpAdvc.CLD_ID,    
       MmShpAdvc.SLOC_ID,    
       MmShpAdvc.ORG_ID,    
       MmShpAdvc.DOC_ID,    
       MmShpAdvc.DOC_DT,    
       MmShpAdvc.SHP_ADV_NO,    
       MmShpAdvc.FY_ID,    
       MmShpAdvc.DOC_ID_PO,    
       MmShpAdvc.DLV_SCHDL_NO,    
       MmShpAdvc.FILE_NO,    
       MmShpAdvc.EO_ID,    
       MmShpAdvc.CURR_ID_SP,    
       MmShpAdvc.CURR_CONV_FCTR,    
       MmShpAdvc.EO_ID_SHP,    
       MmShpAdvc.ADDS_ID_SHP,    
       MmShpAdvc.BOL_AWB_NO,    
       MmShpAdvc.BOL_AWB_DT,    
       MmShpAdvc.EO_SHP_NO,    
       MmShpAdvc.EO_SHP_DT,    
       MmShpAdvc.ETD,    
       MmShpAdvc.ETA,    
       MmShpAdvc.SHP_STAT,    
       MmShpAdvc.AUTH_STAT,    
       MmShpAdvc.DOC_STAT,    
       MmShpAdvc.USR_ID_CREATE,    
       MmShpAdvc.USR_ID_CREATE_DT,    
       MmShpAdvc.USR_ID_MOD,    
       MmShpAdvc.USR_ID_MOD_DT    
FROM MM$SHP$ADVC MmShpAdvc]]></SQLQuery>
  <ViewAttribute
    Name="CldId"
    IsUpdateable="false"
    IsPersistent="false"
    IsNotNull="true"
    PrecisionRule="true"
    Precision="4"
    Type="java.lang.String"
    ColumnType="VARCHAR2"
    AliasName="CLD_ID"
    Expression="CLD_ID"
    SQLType="VARCHAR">
    <DesignTime>
      <Attr Name="_DisplaySize" Value="4"/>
    </DesignTime>
  </ViewAttribute>
  <ViewAttribute
    Name="SlocId"
    IsUpdateable="false"
    IsPersistent="false"
    IsNotNull="true"
    PrecisionRule="true"
    Precision="5"
    Scale="0"
    Type="java.lang.Integer"
    ColumnType="NUMBER"
    AliasName="SLOC_ID"
    Expression="SLOC_ID"
    SQLType="INTEGER"/>
  <ViewAttribute
    Name="OrgId"
    IsUpdateable="false"
    IsPersistent="false"
    PrecisionRule="true"
    Precision="2"
    Type="java.lang.String"
    ColumnType="VARCHAR2"
    AliasName="ORG_ID"
    Expression="ORG_ID"
    SQLType="VARCHAR">
    <DesignTime>
      <Attr Name="_DisplaySize" Value="2"/>
    </DesignTime>
  </ViewAttribute>
  <ViewAttribute
    Name="DocId"
    IsUpdateable="false"
    IsPersistent="false"
    IsNotNull="true"
    PrecisionRule="true"
    Precision="40"
    Type="java.lang.String"
    ColumnType="VARCHAR2"
    AliasName="DOC_ID"
    Expression="DOC_ID"
    SQLType="VARCHAR">
    <DesignTime>
      <Attr Name="_DisplaySize" Value="40"/>
    </DesignTime>
  </ViewAttribute>
  <ViewAttribute
    Name="DocDt"
    IsUpdateable="false"
    IsPersistent="false"
    PrecisionRule="true"
    Type="java.sql.Timestamp"
    ColumnType="TIMESTAMP"
    AliasName="DOC_DT"
    Expression="DOC_DT"
    SQLType="DATE"/>
  <ViewAttribute
    Name="ShpAdvNo"
    IsUpdateable="false"
    IsPersistent="false"
    PrecisionRule="true"
    Precision="20"
    Type="java.lang.String"
    ColumnType="VARCHAR2"
    AliasName="SHP_ADV_NO"
    Expression="SHP_ADV_NO"
    SQLType="VARCHAR">
    <DesignTime>
      <Attr Name="_DisplaySize" Value="20"/>
    </DesignTime>
  </ViewAttribute>
  <ViewAttribute
    Name="FyId"
    IsUpdateable="false"
    IsPersistent="false"
    PrecisionRule="true"
    Precision="5"
    Scale="0"
    Type="java.lang.Integer"
    ColumnType="NUMBER"
    AliasName="FY_ID"
    Expression="FY_ID"
    SQLType="INTEGER"/>
  <ViewAttribute
    Name="DocIdPo"
    IsUpdateable="false"
    IsPersistent="false"
    PrecisionRule="true"
    Precision="40"
    Type="java.lang.String"
    ColumnType="VARCHAR2"
    AliasName="DOC_ID_PO"
    Expression="DOC_ID_PO"
    SQLType="VARCHAR">
    <DesignTime>
      <Attr Name="_DisplaySize" Value="40"/>
    </DesignTime>
  </ViewAttribute>
  <ViewAttribute
    Name="DlvSchdlNo"
    IsUpdateable="false"
    IsPersistent="false"
    PrecisionRule="true"
    Precision="5"
    Scale="0"
    Type="java.lang.Integer"
    ColumnType="NUMBER"
    AliasName="DLV_SCHDL_NO"
    Expression="DLV_SCHDL_NO"
    SQLType="INTEGER"/>
  <ViewAttribute
    Name="FileNo"
    IsUpdateable="false"
    IsPersistent="false"
    PrecisionRule="true"
    Precision="20"
    Type="java.lang.String"
    ColumnType="VARCHAR2"
    AliasName="FILE_NO"
    Expression="FILE_NO"
    SQLType="VARCHAR">
    <DesignTime>
      <Attr Name="_DisplaySize" Value="20"/>
    </DesignTime>
  </ViewAttribute>
  <ViewAttribute
    Name="EoId"
    IsUpdateable="false"
    IsPersistent="false"
    IsNotNull="true"
    PrecisionRule="true"
    Precision="5"
    Scale="0"
    Type="java.lang.Integer"
    ColumnType="NUMBER"
    AliasName="EO_ID"
    Expression="EO_ID"
    SQLType="INTEGER"/>
  <ViewAttribute
    Name="CurrIdSp"
    IsUpdateable="false"
    IsPersistent="false"
    PrecisionRule="true"
    Precision="5"
    Scale="0"
    Type="java.lang.Integer"
    ColumnType="NUMBER"
    AliasName="CURR_ID_SP"
    Expression="CURR_ID_SP"
    SQLType="INTEGER"/>
  <ViewAttribute
    Name="CurrConvFctr"
    IsUpdateable="false"
    IsPersistent="false"
    PrecisionRule="true"
    Precision="26"
    Scale="6"
    Type="java.math.BigDecimal"
    ColumnType="NUMBER"
    AliasName="CURR_CONV_FCTR"
    Expression="CURR_CONV_FCTR"
    SQLType="NUMERIC"/>
  <ViewAttribute
    Name="EoIdShp"
    IsUpdateable="false"
    IsPersistent="false"
    PrecisionRule="true"
    Precision="5"
    Scale="0"
    Type="java.lang.Integer"
    ColumnType="NUMBER"
    AliasName="EO_ID_SHP"
    Expression="EO_ID_SHP"
    SQLType="INTEGER"/>
  <ViewAttribute
    Name="AddsIdShp"
    IsUpdateable="false"
    IsPersistent="false"
    PrecisionRule="true"
    Precision="20"
    Type="java.lang.String"
    ColumnType="VARCHAR2"
    AliasName="ADDS_ID_SHP"
    Expression="ADDS_ID_SHP"
    SQLType="VARCHAR">
    <DesignTime>
      <Attr Name="_DisplaySize" Value="20"/>
    </DesignTime>
  </ViewAttribute>
  <ViewAttribute
    Name="BolAwbNo"
    IsUpdateable="false"
    IsPersistent="false"
    PrecisionRule="true"
    Precision="50"
    Type="java.lang.String"
    ColumnType="VARCHAR2"
    AliasName="BOL_AWB_NO"
    Expression="BOL_AWB_NO"
    SQLType="VARCHAR">
    <DesignTime>
      <Attr Name="_DisplaySize" Value="50"/>
    </DesignTime>
  </ViewAttribute>
  <ViewAttribute
    Name="BolAwbDt"
    IsUpdateable="false"
    IsPersistent="false"
    PrecisionRule="true"
    Type="java.sql.Timestamp"
    ColumnType="DATE"
    AliasName="BOL_AWB_DT"
    Expression="BOL_AWB_DT"
    SQLType="DATE"/>
  <ViewAttribute
    Name="EoShpNo"
    IsUpdateable="false"
    IsPersistent="false"
    PrecisionRule="true"
    Precision="50"
    Type="java.lang.String"
    ColumnType="VARCHAR2"
    AliasName="EO_SHP_NO"
    Expression="EO_SHP_NO"
    SQLType="VARCHAR">
    <DesignTime>
      <Attr Name="_DisplaySize" Value="50"/>
    </DesignTime>
  </ViewAttribute>
  <ViewAttribute
    Name="EoShpDt"
    IsUpdateable="false"
    IsPersistent="false"
    PrecisionRule="true"
    Type="java.sql.Timestamp"
    ColumnType="DATE"
    AliasName="EO_SHP_DT"
    Expression="EO_SHP_DT"
    SQLType="DATE"/>
  <ViewAttribute
    Name="Etd"
    IsUpdateable="false"
    IsPersistent="false"
    PrecisionRule="true"
    Type="java.sql.Timestamp"
    ColumnType="DATE"
    AliasName="ETD"
    Expression="ETD"
    SQLType="DATE"/>
  <ViewAttribute
    Name="Eta"
    IsUpdateable="false"
    IsPersistent="false"
    PrecisionRule="true"
    Type="java.sql.Timestamp"
    ColumnType="DATE"
    AliasName="ETA"
    Expression="ETA"
    SQLType="DATE"/>
  <ViewAttribute
    Name="ShpStat"
    IsUpdateable="false"
    IsPersistent="false"
    PrecisionRule="true"
    Precision="50"
    Type="java.lang.String"
    ColumnType="VARCHAR2"
    AliasName="SHP_STAT"
    Expression="SHP_STAT"
    SQLType="VARCHAR">
    <DesignTime>
      <Attr Name="_DisplaySize" Value="50"/>
    </DesignTime>
  </ViewAttribute>
  <ViewAttribute
    Name="AuthStat"
    IsUpdateable="false"
    IsPersistent="false"
    IsNotNull="true"
    PrecisionRule="true"
    Precision="1"
    Type="java.lang.String"
    ColumnType="VARCHAR2"
    AliasName="AUTH_STAT"
    Expression="AUTH_STAT"
    SQLType="VARCHAR">
    <DesignTime>
      <Attr Name="_DisplaySize" Value="1"/>
    </DesignTime>
  </ViewAttribute>
  <ViewAttribute
    Name="DocStat"
    IsUpdateable="false"
    IsPersistent="false"
    PrecisionRule="true"
    Precision="5"
    Scale="0"
    Type="java.lang.Integer"
    ColumnType="NUMBER"
    AliasName="DOC_STAT"
    Expression="DOC_STAT"
    SQLType="INTEGER"/>
  <ViewAttribute
    Name="UsrIdCreate"
    IsUpdateable="false"
    IsPersistent="false"
    IsNotNull="true"
    PrecisionRule="true"
    Precision="5"
    Scale="0"
    Type="java.lang.Integer"
    ColumnType="NUMBER"
    AliasName="USR_ID_CREATE"
    Expression="USR_ID_CREATE"
    SQLType="INTEGER"/>
  <ViewAttribute
    Name="UsrIdCreateDt"
    IsUpdateable="false"
    IsPersistent="false"
    IsNotNull="true"
    PrecisionRule="true"
    Type="java.sql.Timestamp"
    ColumnType="DATE"
    AliasName="USR_ID_CREATE_DT"
    Expression="USR_ID_CREATE_DT"
    SQLType="DATE"/>
  <ViewAttribute
    Name="UsrIdMod"
    IsUpdateable="false"
    IsPersistent="false"
    PrecisionRule="true"
    Precision="5"
    Scale="0"
    Type="java.lang.Integer"
    ColumnType="NUMBER"
    AliasName="USR_ID_MOD"
    Expression="USR_ID_MOD"
    SQLType="INTEGER"/>
  <ViewAttribute
    Name="UsrIdModDt"
    IsUpdateable="false"
    IsPersistent="false"
    PrecisionRule="true"
    Type="java.sql.Timestamp"
    ColumnType="DATE"
    AliasName="USR_ID_MOD_DT"
    Expression="USR_ID_MOD_DT"
    SQLType="DATE"/>
  <AttrArray Name="KeyAttributes">
    <Item Value="CldId"/>
    <Item Value="SlocId"/>
    <Item Value="DocId"/>
  </AttrArray>
</ViewObject>
