<?xml version="1.0" encoding="windows-1252" ?>
<!DOCTYPE AppModule SYSTEM "jbo_03_01.dtd">
<!---->
<AppModule
  xmlns="http://xmlns.oracle.com/bc4j"
  Name="HcmSalarySetupAM"
  Version="12.1.3.10.8"
  InheritPersonalization="merge"
  ClearCacheOnRollback="true"
  ComponentClass="hcmsalarysetup.model.modules.HcmSalarySetupAMImpl"
  ComponentInterface="hcmsalarysetup.model.modules.common.HcmSalarySetupAM">
  <DesignTime>
    <Attr Name="_isCodegen" Value="true"/>
  </DesignTime>
  <Properties>
    <SchemaBasedProperties>
      <LABEL
        ResId="hcmsalarysetup.model.modules.HcmSalarySetupAM_LABEL"/>
    </SchemaBasedProperties>
  </Properties>
  <ViewUsage
    Name="DualSearch"
    ViewObjectName="hcmsalarysetup.model.views.DualSearchVO"/>
  <ViewUsage
    Name="OrgHcmSalary"
    ViewObjectName="hcmsalarysetup.model.views.OrgHcmSalaryVO">
    <ViewCriteriaUsage
      Name="searchOrgHcmSalaryCriteria"
      FullName="hcmsalarysetup.model.views.OrgHcmSalaryVO.searchOrgHcmSalaryCriteria"/>
  </ViewUsage>
  <ViewUsage
    Name="OrgHcmSalary1"
    ViewObjectName="hcmsalarysetup.model.views.OrgHcmSalaryVO"/>
  <ViewUsage
    Name="LovSalId"
    ViewObjectName="hcmsalarysetup.model.views.LovSalIdVO"/>
  <ViewUsage
    Name="LovEmpSal1"
    ViewObjectName="hcmsalarysetup.model.views.LovEmpSalVO"/>
  <ViewUsage
    Name="Lovhcmempsal1"
    ViewObjectName="hcmsalarysetup.model.views.LovhcmempsalVO"/>
  <ViewUsage
    Name="LOVhcmemprefsal1"
    ViewObjectName="hcmsalarysetup.model.views.LOVhcmemprefsalVO"/>
  <ViewUsage
    Name="OrgHcmSalSub"
    ViewObjectName="hcmsalarysetup.model.views.OrgHcmSalSubVO"/>
  <ViewUsage
    Name="LovSubSalType"
    ViewObjectName="hcmsalarysetup.model.views.LovSubSalType"/>
  <ViewUsage
    Name="cheakOrgHcmPrfVO1"
    ViewObjectName="hcmsalarysetup.model.views.cheakOrgHcmPrfVO"/>
  <ViewLinkUsage
    Name="OrgHcmSalSubVL1"
    ViewLinkObjectName="hcmsalarysetup.model.views.link.OrgHcmSalSubVL"
    SrcViewUsageName="hcmsalarysetup.model.modules.HcmSalarySetupAM.OrgHcmSalary"
    DstViewUsageName="hcmsalarysetup.model.modules.HcmSalarySetupAM.OrgHcmSalSub"
    Reversed="false"/>
  <ClientInterface
    Name="__clientInterface">
    <Method
      Name="setbindVarOnLoad"
      MethodName="setbindVarOnLoad">
      <Return
        Name="_return_type_"
        Type="void"/>
      <Parameter
        Name="hoOrgId"
        Type="java.lang.String"/>
      <Parameter
        Name="slocId"
        Type="java.lang.Integer"/>
      <Parameter
        Name="orgId"
        Type="java.lang.String"/>
      <Parameter
        Name="cldId"
        Type="java.lang.String"/>
    </Method>
    <Method
      Name="chkDuplicateNotation"
      MethodName="chkDuplicateNotation">
      <Return
        Name="_return_type_"
        Type="java.lang.String"/>
      <Parameter
        Name="notation"
        Type="java.lang.String"/>
    </Method>
    <Method
      Name="fieldValueReset"
      MethodName="fieldValueReset">
      <Return
        Name="_return_type_"
        Type="void"/>
    </Method>
    <Method
      Name="chkSalIdToDel"
      MethodName="chkSalIdToDel">
      <Return
        Name="_return_type_"
        Type="java.lang.String"/>
    </Method>
    <Method
      Name="chkValidStrtdt"
      MethodName="chkValidStrtdt">
      <Return
        Name="_return_type_"
        Type="java.lang.String"/>
      <Parameter
        Name="strtDt"
        Type="oracle.jbo.domain.Timestamp"/>
    </Method>
    <Method
      Name="chkEnddate"
      MethodName="chkEnddate">
      <Return
        Name="_return_type_"
        Type="java.lang.String"/>
      <Parameter
        Name="strtDt"
        Type="oracle.jbo.domain.Timestamp"/>
    </Method>
    <Method
      Name="Checksalcomponentlink"
      MethodName="Checksalcomponentlink">
      <Return
        Name="_return_type_"
        Type="java.lang.String"/>
    </Method>
    <Method
      Name="executeLovSalIdVoOnCrt1"
      MethodName="executeLovSalIdVoOnCrt">
      <Return
        Name="_return_type_"
        Type="void"/>
    </Method>
    <Method
      Name="isGlLinkined"
      MethodName="isGlLinkined">
      <Return
        Name="_return_type_"
        Type="java.lang.String"/>
    </Method>
    <Method
      Name="setDefltValuse"
      MethodName="setDefltValuse">
      <Return
        Name="_return_type_"
        Type="void"/>
    </Method>
    <Method
      Name="Checksalcomponentlink"
      MethodName="Checksalcomponentlink">
      <Return
        Name="_return_type_"
        Type="java.lang.String"/>
    </Method>
    <Method
      Name="chkDuplicateNotation"
      MethodName="chkDuplicateNotation">
      <Return
        Name="_return_type_"
        Type="java.lang.String"/>
      <Parameter
        Name="notation"
        Type="java.lang.String"/>
    </Method>
    <Method
      Name="chkEnddate"
      MethodName="chkEnddate">
      <Return
        Name="_return_type_"
        Type="java.lang.String"/>
      <Parameter
        Name="strtDt"
        Type="oracle.jbo.domain.Timestamp"/>
    </Method>
    <Method
      Name="chkSalIdToDel"
      MethodName="chkSalIdToDel">
      <Return
        Name="_return_type_"
        Type="java.lang.String"/>
    </Method>
    <Method
      Name="chkSubSalCompAction"
      MethodName="chkSubSalCompAction">
      <Return
        Name="_return_type_"
        Type="java.lang.String"/>
      <Parameter
        Name="subSalId"
        Type="java.lang.String"/>
    </Method>
    <Method
      Name="chkValidStrtdt"
      MethodName="chkValidStrtdt">
      <Return
        Name="_return_type_"
        Type="java.lang.String"/>
      <Parameter
        Name="strtDt"
        Type="oracle.jbo.domain.Timestamp"/>
    </Method>
    <Method
      Name="executeLovSalIdVoOnCrt1"
      MethodName="executeLovSalIdVoOnCrt">
      <Return
        Name="_return_type_"
        Type="void"/>
    </Method>
    <Method
      Name="fieldValueReset"
      MethodName="fieldValueReset">
      <Return
        Name="_return_type_"
        Type="void"/>
    </Method>
    <Method
      Name="isGlLinkined"
      MethodName="isGlLinkined">
      <Return
        Name="_return_type_"
        Type="java.lang.String"/>
    </Method>
    <Method
      Name="setDefltValuse"
      MethodName="setDefltValuse">
      <Return
        Name="_return_type_"
        Type="void"/>
    </Method>
    <Method
      Name="setbindVarOnLoad"
      MethodName="setbindVarOnLoad">
      <Return
        Name="_return_type_"
        Type="void"/>
      <Parameter
        Name="hoOrgId"
        Type="java.lang.String"/>
      <Parameter
        Name="slocId"
        Type="java.lang.Integer"/>
      <Parameter
        Name="orgId"
        Type="java.lang.String"/>
      <Parameter
        Name="cldId"
        Type="java.lang.String"/>
    </Method>
    <Method
      Name="searchSalaryComp"
      MethodName="searchSalaryComp">
      <Return
        Name="_return_type_"
        Type="void"/>
      <Parameter
        Name="salId"
        Type="java.lang.String"/>
      <Parameter
        Name="behav"
        Type="java.lang.Integer"/>
      <Parameter
        Name="frmDt"
        Type="oracle.jbo.domain.Timestamp"/>
      <Parameter
        Name="toDt"
        Type="oracle.jbo.domain.Timestamp"/>
      <Parameter
        Name="isOthrDedChk"
        Type="java.lang.String"/>
    </Method>
    <Method
      Name="chkDuplicateSeqNo"
      MethodName="chkDuplicateSeqNo">
      <Return
        Name="_return_type_"
        Type="java.lang.String"/>
      <Parameter
        Name="seqNo"
        Type="java.lang.Integer"/>
    </Method>
    <Method
      Name="validateLegacyCodeId"
      MethodName="validateLegacyCodeId">
      <Return
        Name="_return_type_"
        Type="java.lang.String"/>
      <Parameter
        Name="legacyCodeId"
        Type="java.lang.String"/>
    </Method>
  </ClientInterface>
  <ResourceBundle>
    <PropertiesBundle
      PropertiesFile="hcmsalarysetup.model.ModelBundle"/>
  </ResourceBundle>
</AppModule>
