<?xml version="1.0" encoding="UTF-8" ?>
<!DOCTYPE ViewLink SYSTEM "jbo_03_01.dtd">
<!---->
<ViewLink
  xmlns="http://xmlns.oracle.com/bc4j"
  Name="ExcPdoToExcPdoJobCardVL"
  Version="12.1.3.10.8"
  InheritPersonalization="merge">
  <Properties>
    <SchemaBasedProperties>
      <LABEL
        ResId="mnfPlanningBoardApp.model.links.ExcPdoToExcPdoJobCardVL_LABEL"/>
    </SchemaBasedProperties>
  </Properties>
  <ViewLinkDefEnd
    Name="LISTExcPdoVO"
    Cardinality="1"
    Source="true"
    Owner="mnfPlanningBoardApp.model.views.LISTExcPdoVO">
    <DesignTime>
      <Attr Name="_finderName" Value="LISTExcPdoVO"/>
      <Attr Name="_isUpdateable" Value="true"/>
    </DesignTime>
    <AttrArray Name="Attributes">
      <Item Value="mnfPlanningBoardApp.model.views.LISTExcPdoVO.CldId"/>
      <Item Value="mnfPlanningBoardApp.model.views.LISTExcPdoVO.HoOrgId"/>
      <Item Value="mnfPlanningBoardApp.model.views.LISTExcPdoVO.OrgId"/>
      <Item Value="mnfPlanningBoardApp.model.views.LISTExcPdoVO.SlocId"/>
      <Item Value="mnfPlanningBoardApp.model.views.LISTExcPdoVO.PdoDocId"/>
    </AttrArray>
  </ViewLinkDefEnd>
  <ViewLinkDefEnd
    Name="LISTExcPdoJobCardVO"
    Cardinality="-1"
    Owner="mnfPlanningBoardApp.model.views.LISTExcPdoJobCardVO">
    <DesignTime>
      <Attr Name="_finderName" Value="LISTExcPdoJobCardVO"/>
      <Attr Name="_isUpdateable" Value="true"/>
    </DesignTime>
    <AttrArray Name="Attributes">
      <Item Value="mnfPlanningBoardApp.model.views.LISTExcPdoJobCardVO.CldId"/>
      <Item Value="mnfPlanningBoardApp.model.views.LISTExcPdoJobCardVO.HoOrgId"/>
      <Item Value="mnfPlanningBoardApp.model.views.LISTExcPdoJobCardVO.OrgId"/>
      <Item Value="mnfPlanningBoardApp.model.views.LISTExcPdoJobCardVO.SlocId"/>
      <Item Value="mnfPlanningBoardApp.model.views.LISTExcPdoJobCardVO.DocId"/>
    </AttrArray>
  </ViewLinkDefEnd>
  <ResourceBundle>
    <PropertiesBundle
      PropertiesFile="mnfPlanningBoardApp.model.ModelBundle"/>
  </ResourceBundle>
</ViewLink>
